{"assetProfile": {"address1": "101 Tuas South Avenue 2", "city": "Singapore", "zip": "637226", "country": "Singapore", "phone": "65 6653 2299", "website": "https://esgl.asia", "industry": "Waste Management", "industryKey": "waste-management", "industryDisp": "Waste Management", "sector": "Industrials", "sectorKey": "industrials", "sectorDisp": "Industrials", "longBusinessSummary": "ESGL Holdings Limited, through its subsidiary, Environmental Solutions (Asia) Pte. Ltd., operates as a waste management, treatment, and recycling company. It engages in the collection and recycling of hazardous and non-hazardous industrial waste from pharmaceutical, semiconductor, petrochemical, and electroplating companies. The company was founded in 1999 and is headquartered in Singapore.", "fullTimeEmployees": 79, "companyOfficers": [{"maxAge": 1, "name": "Mr. Leng Chuang  Quek", "age": 55, "title": "Chairman & CEO", "yearBorn": 1969, "exercisedValue": {"raw": 0, "fmt": null, "longFmt": "0"}, "unexercisedValue": {"raw": 0, "fmt": null, "longFmt": "0"}}, {"maxAge": 1, "name": "Mr. Shian Ching  Ho", "age": 52, "title": "Chief Financial Officer", "yearBorn": 1972, "exercisedValue": {"raw": 0, "fmt": null, "longFmt": "0"}, "unexercisedValue": {"raw": 0, "fmt": null, "longFmt": "0"}}, {"maxAge": 1, "name": "Mr. Meng Seng  Lee", "age": 54, "title": "Chief Operating Officer", "yearBorn": 1970, "exercisedValue": {"raw": 0, "fmt": null, "longFmt": "0"}, "unexercisedValue": {"raw": 0, "fmt": null, "longFmt": "0"}}, {"maxAge": 1, "name": "Mr. Beng Hui  Law", "age": 46, "title": "Chief Growth & Sustainability Officer and Director", "yearBorn": 1978, "exercisedValue": {"raw": 0, "fmt": null, "longFmt": "0"}, "unexercisedValue": {"raw": 0, "fmt": null, "longFmt": "0"}}], "executiveTeam": [], "maxAge": 86400}, "calendarEvents": {"maxAge": 1, "earnings": {"earningsDate": [], "earningsCallDate": [], "isEarningsDateEstimate": false, "earningsAverage": {}, "earningsLow": {}, "earningsHigh": {}, "revenueAverage": {}, "revenueLow": {}, "revenueHigh": {}}, "exDividendDate": {}, "dividendDate": {}}, "earningsTrend": {"trend": [{"maxAge": 1, "period": "0q", "endDate": "2023-03-31", "growth": {}, "earningsEstimate": {"avg": {}, "low": {}, "high": {}, "yearAgoEps": {}, "numberOfAnalysts": {}, "growth": {}, "earningsCurrency": null}, "revenueEstimate": {"avg": {"raw": 0, "fmt": null, "longFmt": "0"}, "low": {"raw": 0, "fmt": null, "longFmt": "0"}, "high": {"raw": 0, "fmt": null, "longFmt": "0"}, "numberOfAnalysts": {"raw": 0, "fmt": null, "longFmt": "0"}, "yearAgoRevenue": {}, "growth": {}, "revenueCurrency": null}, "epsTrend": {"current": {}, "7daysAgo": {}, "30daysAgo": {}, "60daysAgo": {}, "90daysAgo": {}, "epsTrendCurrency": null}, "epsRevisions": {"upLast7days": {}, "upLast30days": {}, "downLast30days": {}, "downLast7Days": {}, "downLast90days": {}, "epsRevisionsCurrency": null}}, {"maxAge": 1, "period": "+1q", "endDate": null, "growth": {}, "earningsEstimate": {"avg": {}, "low": {}, "high": {}, "yearAgoEps": {}, "numberOfAnalysts": {}, "growth": {}, "earningsCurrency": null}, "revenueEstimate": {"avg": {"raw": 0, "fmt": null, "longFmt": "0"}, "low": {"raw": 0, "fmt": null, "longFmt": "0"}, "high": {"raw": 0, "fmt": null, "longFmt": "0"}, "numberOfAnalysts": {"raw": 0, "fmt": null, "longFmt": "0"}, "yearAgoRevenue": {}, "growth": {}, "revenueCurrency": null}, "epsTrend": {"current": {}, "7daysAgo": {}, "30daysAgo": {}, "60daysAgo": {}, "90daysAgo": {}, "epsTrendCurrency": null}, "epsRevisions": {"upLast7days": {}, "upLast30days": {}, "downLast30days": {}, "downLast7Days": {}, "downLast90days": {}, "epsRevisionsCurrency": null}}, {"maxAge": 1, "period": "0y", "endDate": null, "growth": {}, "earningsEstimate": {"avg": {}, "low": {}, "high": {}, "yearAgoEps": {}, "numberOfAnalysts": {}, "growth": {}, "earningsCurrency": null}, "revenueEstimate": {"avg": {"raw": 0, "fmt": null, "longFmt": "0"}, "low": {"raw": 0, "fmt": null, "longFmt": "0"}, "high": {"raw": 0, "fmt": null, "longFmt": "0"}, "numberOfAnalysts": {"raw": 0, "fmt": null, "longFmt": "0"}, "yearAgoRevenue": {}, "growth": {}, "revenueCurrency": null}, "epsTrend": {"current": {}, "7daysAgo": {}, "30daysAgo": {}, "60daysAgo": {}, "90daysAgo": {}, "epsTrendCurrency": null}, "epsRevisions": {"upLast7days": {}, "upLast30days": {}, "downLast30days": {}, "downLast7Days": {}, "downLast90days": {}, "epsRevisionsCurrency": null}}, {"maxAge": 1, "period": "+1y", "endDate": null, "growth": {}, "earningsEstimate": {"avg": {}, "low": {}, "high": {}, "yearAgoEps": {}, "numberOfAnalysts": {}, "growth": {}, "earningsCurrency": null}, "revenueEstimate": {"avg": {"raw": 0, "fmt": null, "longFmt": "0"}, "low": {"raw": 0, "fmt": null, "longFmt": "0"}, "high": {"raw": 0, "fmt": null, "longFmt": "0"}, "numberOfAnalysts": {"raw": 0, "fmt": null, "longFmt": "0"}, "yearAgoRevenue": {}, "growth": {}, "revenueCurrency": null}, "epsTrend": {"current": {}, "7daysAgo": {}, "30daysAgo": {}, "60daysAgo": {}, "90daysAgo": {}, "epsTrendCurrency": null}, "epsRevisions": {"upLast7days": {}, "upLast30days": {}, "downLast30days": {}, "downLast7Days": {}, "downLast90days": {}, "epsRevisionsCurrency": null}}], "defaultMethodology": "nongaap", "maxAge": 1}, "earningsHistory": {"history": [], "defaultMethodology": "nongaap", "maxAge": 86400}, "financialData": {"maxAge": 86400, "currentPrice": {"raw": 3.85, "fmt": "3.85"}, "targetHighPrice": {}, "targetLowPrice": {}, "targetMeanPrice": {}, "targetMedianPrice": {}, "recommendationMean": {}, "recommendationKey": "none", "numberOfAnalystOpinions": {}, "totalCash": {"raw": 312547, "fmt": "312.55k", "longFmt": "312,547"}, "totalCashPerShare": {"raw": 0.007, "fmt": "0.01"}, "ebitda": {"raw": -1811999, "fmt": "-1.81M", "longFmt": "-1,811,999"}, "totalDebt": {"raw": 6193813, "fmt": "6.19M", "longFmt": "6,193,813"}, "quickRatio": {"raw": 0.119, "fmt": "0.12"}, "currentRatio": {"raw": 0.182, "fmt": "0.18"}, "totalRevenue": {"raw": 5328277, "fmt": "5.33M", "longFmt": "5,328,277"}, "debtToEquity": {"raw": 45.764, "fmt": "45.76%"}, "revenuePerShare": {"raw": 0.146, "fmt": "0.15"}, "returnOnAssets": {"raw": -0.07869, "fmt": "-7.87%"}, "returnOnEquity": {"raw": -0.23183, "fmt": "-23.18%"}, "grossProfits": {"raw": 2825689, "fmt": "2.83M", "longFmt": "2,825,689"}, "freeCashflow": {"raw": -5031612, "fmt": "-5.03M", "longFmt": "-5,031,612"}, "operatingCashflow": {"raw": -2130483, "fmt": "-2.13M", "longFmt": "-2,130,483"}, "earningsGrowth": {}, "revenueGrowth": {"raw": -0.221, "fmt": "-22.10%"}, "grossMargins": {"raw": 0.53032, "fmt": "53.03%"}, "ebitdaMargins": {"raw": -0.34007, "fmt": "-34.01%"}, "operatingMargins": {"raw": -1.02243, "fmt": "-102.24%"}, "profitMargins": {"raw": -0.51218, "fmt": "-51.22%"}, "financialCurrency": "USD"}}