{"assetProfile": {"address1": "11 Bermudiana Road", "address2": "Mailboxes Suite 1141", "city": "Pembroke", "zip": "HM 08", "country": "Bermuda", "phone": "441 298 4900", "website": "https://www.kestrelgroup.com", "industry": "Insurance Brokers", "industryKey": "insurance-brokers", "industryDisp": "Insurance Brokers", "sector": "Financial Services", "sectorKey": "financial-services", "sectorDisp": "Financial Services", "longBusinessSummary": "Kestrel Group Ltd engages in provision of fronting services to insurance program managers, MGAs, reinsurers, and reinsurance brokers in Bermuda. The company operates through two segments: Program Services and Legacy Reinsurance. Kestrel Group Ltd is based in Pembroke, Bermuda.", "companyOfficers": [{"maxAge": 1, "name": "Mr. Terry Lee Ledbetter", "age": 71, "title": "Executive Chairman", "yearBorn": 1953, "exercisedValue": {"raw": 0, "fmt": null, "longFmt": "0"}, "unexercisedValue": {"raw": 0, "fmt": null, "longFmt": "0"}}, {"maxAge": 1, "name": "Mr. Bradford Luke Ledbetter", "age": 42, "title": "CEO & Director", "yearBorn": 1982, "exercisedValue": {"raw": 0, "fmt": null, "longFmt": "0"}, "unexercisedValue": {"raw": 0, "fmt": null, "longFmt": "0"}}, {"maxAge": 1, "name": "Mr. Patrick Joseph Haveron CPA", "age": 63, "title": "President & CFO", "yearBorn": 1961, "exercisedValue": {"raw": 0, "fmt": null, "longFmt": "0"}, "unexercisedValue": {"raw": 0, "fmt": null, "longFmt": "0"}}], "auditRisk": 9, "boardRisk": 8, "compensationRisk": 7, "shareHolderRightsRisk": 1, "overallRisk": 4, "governanceEpochDate": 1761955200, "executiveTeam": [], "maxAge": 86400}, "calendarEvents": {"maxAge": 1, "earnings": {"earningsDate": [{"raw": 1754477940, "fmt": "2025-08-06"}, {"raw": 1754913600, "fmt": "2025-08-11"}], "earningsCallDate": [], "isEarningsDateEstimate": true, "earningsAverage": {}, "earningsLow": {}, "earningsHigh": {}, "revenueAverage": {}, "revenueLow": {}, "revenueHigh": {}}, "exDividendDate": {}, "dividendDate": {}}, "earningsTrend": {"trend": [{"maxAge": 1, "period": "0q", "endDate": null, "growth": {}, "earningsEstimate": {"avg": {}, "low": {}, "high": {}, "yearAgoEps": {}, "numberOfAnalysts": {}, "growth": {}, "earningsCurrency": null}, "revenueEstimate": {"avg": {"raw": 0, "fmt": null, "longFmt": "0"}, "low": {"raw": 0, "fmt": null, "longFmt": "0"}, "high": {"raw": 0, "fmt": null, "longFmt": "0"}, "numberOfAnalysts": {"raw": 0, "fmt": null, "longFmt": "0"}, "yearAgoRevenue": {}, "growth": {}, "revenueCurrency": null}, "epsTrend": {"current": {}, "7daysAgo": {}, "30daysAgo": {}, "60daysAgo": {}, "90daysAgo": {}, "epsTrendCurrency": null}, "epsRevisions": {"upLast7days": {}, "upLast30days": {}, "downLast30days": {}, "downLast7Days": {}, "downLast90days": {}, "epsRevisionsCurrency": null}}, {"maxAge": 1, "period": "+1q", "endDate": null, "growth": {}, "earningsEstimate": {"avg": {}, "low": {}, "high": {}, "yearAgoEps": {}, "numberOfAnalysts": {}, "growth": {}, "earningsCurrency": null}, "revenueEstimate": {"avg": {"raw": 0, "fmt": null, "longFmt": "0"}, "low": {"raw": 0, "fmt": null, "longFmt": "0"}, "high": {"raw": 0, "fmt": null, "longFmt": "0"}, "numberOfAnalysts": {"raw": 0, "fmt": null, "longFmt": "0"}, "yearAgoRevenue": {}, "growth": {}, "revenueCurrency": null}, "epsTrend": {"current": {}, "7daysAgo": {}, "30daysAgo": {}, "60daysAgo": {}, "90daysAgo": {}, "epsTrendCurrency": null}, "epsRevisions": {"upLast7days": {}, "upLast30days": {}, "downLast30days": {}, "downLast7Days": {}, "downLast90days": {}, "epsRevisionsCurrency": null}}, {"maxAge": 1, "period": "0y", "endDate": null, "growth": {}, "earningsEstimate": {"avg": {}, "low": {}, "high": {}, "yearAgoEps": {}, "numberOfAnalysts": {}, "growth": {}, "earningsCurrency": null}, "revenueEstimate": {"avg": {"raw": 0, "fmt": null, "longFmt": "0"}, "low": {"raw": 0, "fmt": null, "longFmt": "0"}, "high": {"raw": 0, "fmt": null, "longFmt": "0"}, "numberOfAnalysts": {"raw": 0, "fmt": null, "longFmt": "0"}, "yearAgoRevenue": {}, "growth": {}, "revenueCurrency": null}, "epsTrend": {"current": {}, "7daysAgo": {}, "30daysAgo": {}, "60daysAgo": {}, "90daysAgo": {}, "epsTrendCurrency": null}, "epsRevisions": {"upLast7days": {}, "upLast30days": {}, "downLast30days": {}, "downLast7Days": {}, "downLast90days": {}, "epsRevisionsCurrency": null}}, {"maxAge": 1, "period": "+1y", "endDate": null, "growth": {}, "earningsEstimate": {"avg": {}, "low": {}, "high": {}, "yearAgoEps": {}, "numberOfAnalysts": {}, "growth": {}, "earningsCurrency": null}, "revenueEstimate": {"avg": {"raw": 0, "fmt": null, "longFmt": "0"}, "low": {"raw": 0, "fmt": null, "longFmt": "0"}, "high": {"raw": 0, "fmt": null, "longFmt": "0"}, "numberOfAnalysts": {"raw": 0, "fmt": null, "longFmt": "0"}, "yearAgoRevenue": {}, "growth": {}, "revenueCurrency": null}, "epsTrend": {"current": {}, "7daysAgo": {}, "30daysAgo": {}, "60daysAgo": {}, "90daysAgo": {}, "epsTrendCurrency": null}, "epsRevisions": {"upLast7days": {}, "upLast30days": {}, "downLast30days": {}, "downLast7Days": {}, "downLast90days": {}, "epsRevisionsCurrency": null}}], "defaultMethodology": "nongaap", "maxAge": 1}, "earningsHistory": {"history": [], "defaultMethodology": "nongaap", "maxAge": 86400}, "financialData": {"maxAge": 86400, "currentPrice": {"raw": 22.71, "fmt": "22.71"}, "targetHighPrice": {}, "targetLowPrice": {}, "targetMeanPrice": {}, "targetMedianPrice": {}, "recommendationMean": {}, "recommendationKey": "none", "numberOfAnalystOpinions": {}, "totalCash": {"raw": 18951000, "fmt": "18.95M", "longFmt": "18,951,000"}, "totalCashPerShare": {"raw": 2.448, "fmt": "2.45"}, "ebitda": {}, "totalDebt": {"raw": 175943008, "fmt": "175.94M", "longFmt": "175,943,008"}, "quickRatio": {"raw": 0.202, "fmt": "0.20"}, "currentRatio": {"raw": 6.001, "fmt": "6.00"}, "totalRevenue": {"raw": 9983137, "fmt": "9.98M", "longFmt": "9,983,137"}, "debtToEquity": {"raw": 117.229, "fmt": "117.23%"}, "revenuePerShare": {"raw": 1.289, "fmt": "1.29"}, "returnOnAssets": {}, "returnOnEquity": {}, "grossProfits": {"raw": 15550137, "fmt": "15.55M", "longFmt": "15,550,137"}, "freeCashflow": {}, "operatingCashflow": {"raw": -21438840, "fmt": "-21.44M", "longFmt": "-21,438,840"}, "earningsGrowth": {}, "revenueGrowth": {"raw": 7.803, "fmt": "780.30%"}, "grossMargins": {"raw": 1.5576401, "fmt": "155.76%"}, "ebitdaMargins": {"raw": 0.0, "fmt": "0.00%"}, "operatingMargins": {"raw": 1.3937, "fmt": "139.37%"}, "profitMargins": {"raw": 7.09008, "fmt": "709.01%"}, "financialCurrency": "USD"}}