{"assetProfile": {"address1": "950 Tower Lane", "address2": "12th Floor, Suite No. 1200", "city": "Foster City", "state": "CA", "zip": "94404", "country": "United States", "phone": "650 587 7700", "website": "https://www.quinstreet.com", "industry": "Advertising Agencies", "industryKey": "advertising-agencies", "industryDisp": "Advertising Agencies", "sector": "Communication Services", "sectorKey": "communication-services", "sectorDisp": "Communication Services", "longBusinessSummary": "QuinStreet, Inc., an online performance marketing company, provides customer acquisition services for its clients in the United States and internationally. The company offers online marketing services, such as qualified clicks, leads, calls, applications, and customers through its websites or third-party publishers to financial and home services industries. It also develops the QuinStreet Rating Platform product for insurance agents and the CloudControlMedia that provides performance marketing agency and technology services to clients in financial services, education, and other markets. The company was incorporated in 1999 and is headquartered in Foster City, California.", "fullTimeEmployees": 938, "companyOfficers": [{"maxAge": 1, "name": "Mr. Douglas  Valenti", "age": 64, "title": "Chairman, President & CEO", "yearBorn": 1960, "fiscalYear": 2025, "totalPay": {"raw": 590000, "fmt": "590k", "longFmt": "590,000"}, "exercisedValue": {"raw": 0, "fmt": null, "longFmt": "0"}, "unexercisedValue": {"raw": 0, "fmt": null, "longFmt": "0"}}, {"maxAge": 1, "name": "Mr. Gregory  Wong", "age": 51, "title": "Chief Financial Officer", "yearBorn": 1973, "fiscalYear": 2025, "totalPay": {"raw": 526882, "fmt": "526.88k", "longFmt": "526,882"}, "exercisedValue": {"raw": 557600, "fmt": "557.6k", "longFmt": "557,600"}, "unexercisedValue": {"raw": 0, "fmt": null, "longFmt": "0"}}, {"maxAge": 1, "name": "Mr. Timothy J. Stevens J.D.", "age": 57, "title": "Chief Operating Officer", "yearBorn": 1967, "fiscalYear": 2025, "totalPay": {"raw": 496445, "fmt": "496.44k", "longFmt": "496,445"}, "exercisedValue": {"raw": 0, "fmt": null, "longFmt": "0"}, "unexercisedValue": {"raw": 0, "fmt": null, "longFmt": "0"}}, {"maxAge": 1, "name": "Ms. Nina  Bhanap", "age": 51, "title": "CTO and President of Product & Technology", "yearBorn": 1973, "fiscalYear": 2025, "totalPay": {"raw": 599922, "fmt": "599.92k", "longFmt": "599,922"}, "exercisedValue": {"raw": 0, "fmt": null, "longFmt": "0"}, "unexercisedValue": {"raw": 0, "fmt": null, "longFmt": "0"}}, {"maxAge": 1, "name": "Mr. Martin J. Collins J.D.", "age": 60, "title": "Chief Legal & Privacy Officer", "yearBorn": 1964, "fiscalYear": 2025, "totalPay": {"raw": 472860, "fmt": "472.86k", "longFmt": "472,860"}, "exercisedValue": {"raw": 0, "fmt": null, "longFmt": "0"}, "unexercisedValue": {"raw": 0, "fmt": null, "longFmt": "0"}}, {"maxAge": 1, "name": "Mr. Robert Anthony Amparo", "title": "Senior Director of Investor Relations & Finance", "fiscalYear": 2025, "exercisedValue": {"raw": 0, "fmt": null, "longFmt": "0"}, "unexercisedValue": {"raw": 0, "fmt": null, "longFmt": "0"}}, {"maxAge": 1, "name": "Ms. Ashley  Heller", "title": "Chief People Officer", "fiscalYear": 2025, "exercisedValue": {"raw": 0, "fmt": null, "longFmt": "0"}, "unexercisedValue": {"raw": 0, "fmt": null, "longFmt": "0"}}, {"maxAge": 1, "name": "Mr. Peter  Brooks", "age": 51, "title": "Senior Vice President", "yearBorn": 1973, "fiscalYear": 2025, "totalPay": {"raw": 317760, "fmt": "317.76k", "longFmt": "317,760"}, "exercisedValue": {"raw": 0, "fmt": null, "longFmt": "0"}, "unexercisedValue": {"raw": 0, "fmt": null, "longFmt": "0"}}, {"maxAge": 1, "name": "Mr. Jeremy  Crisp", "title": "Senior Vice President of Search Engine Marketing", "fiscalYear": 2025, "exercisedValue": {"raw": 0, "fmt": null, "longFmt": "0"}, "unexercisedValue": {"raw": 0, "fmt": null, "longFmt": "0"}}, {"maxAge": 1, "name": "Mr. Stephen  Chen", "age": 37, "title": "Senior Vice President", "yearBorn": 1987, "fiscalYear": 2025, "totalPay": {"raw": 300108, "fmt": "300.11k", "longFmt": "300,108"}, "exercisedValue": {"raw": 0, "fmt": null, "longFmt": "0"}, "unexercisedValue": {"raw": 0, "fmt": null, "longFmt": "0"}}], "auditRisk": 2, "boardRisk": 5, "compensationRisk": 4, "shareHolderRightsRisk": 7, "overallRisk": 5, "governanceEpochDate": 1761955200, "compensationAsOfEpochDate": 1767139200, "executiveTeam": [], "maxAge": 86400}, "calendarEvents": {"maxAge": 1, "earnings": {"earningsDate": [{"raw": 1762462800, "fmt": "2025-11-06"}], "earningsCallDate": [{"raw": 1762466400, "fmt": "2025-11-06"}], "isEarningsDateEstimate": false, "earningsAverage": {"raw": 0.212, "fmt": "0.21"}, "earningsLow": {"raw": 0.19, "fmt": "0.19"}, "earningsHigh": {"raw": 0.23, "fmt": "0.23"}, "revenueAverage": {"raw": 279912600, "fmt": "279.91M", "longFmt": "279,912,600"}, "revenueLow": {"raw": 279219000, "fmt": "279.22M", "longFmt": "279,219,000"}, "revenueHigh": {"raw": 280644000, "fmt": "280.64M", "longFmt": "280,644,000"}}, "exDividendDate": {}, "dividendDate": {}}, "earningsTrend": {"trend": [{"maxAge": 1, "period": "0q", "endDate": "2025-09-30", "growth": {"raw": -0.0364, "fmt": "-3.64%"}, "earningsEstimate": {"avg": {"raw": 0.212, "fmt": "0.21"}, "low": {"raw": 0.19, "fmt": "0.19"}, "high": {"raw": 0.23, "fmt": "0.23"}, "yearAgoEps": {"raw": 0.22, "fmt": "0.22"}, "numberOfAnalysts": {"raw": 5, "fmt": "5", "longFmt": "5"}, "growth": {"raw": -0.0364, "fmt": "-3.64%"}, "earningsCurrency": "USD"}, "revenueEstimate": {"avg": {"raw": 279912600, "fmt": "279.91M", "longFmt": "279,912,600"}, "low": {"raw": 279219000, "fmt": "279.22M", "longFmt": "279,219,000"}, "high": {"raw": 280644000, "fmt": "280.64M", "longFmt": "280,644,000"}, "numberOfAnalysts": {"raw": 5, "fmt": "5", "longFmt": "5"}, "yearAgoRevenue": {"raw": 279219000, "fmt": "279.22M", "longFmt": "279,219,000"}, "growth": {"raw": 0.0025, "fmt": "0.25%"}, "revenueCurrency": "USD"}, "epsTrend": {"current": {"raw": 0.212, "fmt": "0.21"}, "7daysAgo": {"raw": 0.212, "fmt": "0.21"}, "30daysAgo": {"raw": 0.2075, "fmt": "0.21"}, "60daysAgo": {"raw": 0.2075, "fmt": "0.21"}, "90daysAgo": {"raw": 0.26, "fmt": "0.26"}, "epsTrendCurrency": "USD"}, "epsRevisions": {"upLast7days": {"raw": 0, "fmt": null, "longFmt": "0"}, "upLast30days": {"raw": 0, "fmt": null, "longFmt": "0"}, "downLast30days": {"raw": 3, "fmt": "3", "longFmt": "3"}, "downLast7Days": {"raw": 3, "fmt": "3", "longFmt": "3"}, "downLast90days": {}, "epsRevisionsCurrency": "USD"}}, {"maxAge": 1, "period": "+1q", "endDate": "2025-12-31", "growth": {"raw": 0.02, "fmt": "2.00%"}, "earningsEstimate": {"avg": {"raw": 0.204, "fmt": "0.2"}, "low": {"raw": 0.18, "fmt": "0.18"}, "high": {"raw": 0.25, "fmt": "0.25"}, "yearAgoEps": {"raw": 0.2, "fmt": "0.2"}, "numberOfAnalysts": {"raw": 5, "fmt": "5", "longFmt": "5"}, "growth": {"raw": 0.02, "fmt": "2.00%"}, "earningsCurrency": "USD"}, "revenueEstimate": {"avg": {"raw": 273885000, "fmt": "273.88M", "longFmt": "273,885,000"}, "low": {"raw": 264985000, "fmt": "264.99M", "longFmt": "264,985,000"}, "high": {"raw": 282119000, "fmt": "282.12M", "longFmt": "282,119,000"}, "numberOfAnalysts": {"raw": 5, "fmt": "5", "longFmt": "5"}, "yearAgoRevenue": {"raw": 282596000, "fmt": "282.6M", "longFmt": "282,596,000"}, "growth": {"raw": -0.0308, "fmt": "-3.08%"}, "revenueCurrency": "USD"}, "epsTrend": {"current": {"raw": 0.204, "fmt": "0.2"}, "7daysAgo": {"raw": 0.204, "fmt": "0.2"}, "30daysAgo": {"raw": 0.2025, "fmt": "0.2"}, "60daysAgo": {"raw": 0.2025, "fmt": "0.2"}, "90daysAgo": {"raw": 0.235, "fmt": "0.23"}, "epsTrendCurrency": "USD"}, "epsRevisions": {"upLast7days": {"raw": 1, "fmt": "1", "longFmt": "1"}, "upLast30days": {"raw": 1, "fmt": "1", "longFmt": "1"}, "downLast30days": {"raw": 3, "fmt": "3", "longFmt": "3"}, "downLast7Days": {"raw": 3, "fmt": "3", "longFmt": "3"}, "downLast90days": {}, "epsRevisionsCurrency": "USD"}}, {"maxAge": 1, "period": "0y", "endDate": "2026-06-30", "growth": {"raw": 0.2045, "fmt": "20.45%"}, "earningsEstimate": {"avg": {"raw": 1.06, "fmt": "1.06"}, "low": {"raw": 1.01, "fmt": "1.01"}, "high": {"raw": 1.13, "fmt": "1.13"}, "yearAgoEps": {"raw": 0.88, "fmt": "0.88"}, "numberOfAnalysts": {"raw": 5, "fmt": "5", "longFmt": "5"}, "growth": {"raw": 0.2045, "fmt": "20.45%"}, "earningsCurrency": "USD"}, "revenueEstimate": {"avg": {"raw": 1192200400, "fmt": "1.19B", "longFmt": "1,192,200,400"}, "low": {"raw": 1176704000, "fmt": "1.18B", "longFmt": "1,176,704,000"}, "high": {"raw": 1202113000, "fmt": "1.2B", "longFmt": "1,202,113,000"}, "numberOfAnalysts": {"raw": 5, "fmt": "5", "longFmt": "5"}, "yearAgoRevenue": {"raw": 1093711000, "fmt": "1.09B", "longFmt": "1,093,711,000"}, "growth": {"raw": 0.090100005, "fmt": "9.01%"}, "revenueCurrency": "USD"}, "epsTrend": {"current": {"raw": 1.06, "fmt": "1.06"}, "7daysAgo": {"raw": 1.062, "fmt": "1.06"}, "30daysAgo": {"raw": 1.05, "fmt": "1.05"}, "60daysAgo": {"raw": 1.05, "fmt": "1.05"}, "90daysAgo": {"raw": 1.058, "fmt": "1.06"}, "epsTrendCurrency": "USD"}, "epsRevisions": {"upLast7days": {"raw": 3, "fmt": "3", "longFmt": "3"}, "upLast30days": {"raw": 3, "fmt": "3", "longFmt": "3"}, "downLast30days": {"raw": 2, "fmt": "2", "longFmt": "2"}, "downLast7Days": {"raw": 2, "fmt": "2", "longFmt": "2"}, "downLast90days": {}, "epsRevisionsCurrency": "USD"}}, {"maxAge": 1, "period": "+1y", "endDate": "2027-06-30", "growth": {"raw": 0.1698, "fmt": "16.98%"}, "earningsEstimate": {"avg": {"raw": 1.24, "fmt": "1.24"}, "low": {"raw": 1.18, "fmt": "1.18"}, "high": {"raw": 1.32, "fmt": "1.32"}, "yearAgoEps": {"raw": 1.06, "fmt": "1.06"}, "numberOfAnalysts": {"raw": 5, "fmt": "5", "longFmt": "5"}, "growth": {"raw": 0.1698, "fmt": "16.98%"}, "earningsCurrency": "USD"}, "revenueEstimate": {"avg": {"raw": 1306116600, "fmt": "1.31B", "longFmt": "1,306,116,600"}, "low": {"raw": 1281578000, "fmt": "1.28B", "longFmt": "1,281,578,000"}, "high": {"raw": 1324246000, "fmt": "1.32B", "longFmt": "1,324,246,000"}, "numberOfAnalysts": {"raw": 5, "fmt": "5", "longFmt": "5"}, "yearAgoRevenue": {"raw": 1192200400, "fmt": "1.19B", "longFmt": "1,192,200,400"}, "growth": {"raw": 0.0956, "fmt": "9.56%"}, "revenueCurrency": "USD"}, "epsTrend": {"current": {"raw": 1.24, "fmt": "1.24"}, "7daysAgo": {"raw": 1.242, "fmt": "1.24"}, "30daysAgo": {"raw": 1.2225, "fmt": "1.22"}, "60daysAgo": {"raw": 1.2225, "fmt": "1.22"}, "90daysAgo": {"raw": 1.18, "fmt": "1.18"}, "epsTrendCurrency": "USD"}, "epsRevisions": {"upLast7days": {"raw": 1, "fmt": "1", "longFmt": "1"}, "upLast30days": {"raw": 1, "fmt": "1", "longFmt": "1"}, "downLast30days": {"raw": 0, "fmt": null, "longFmt": "0"}, "downLast7Days": {"raw": 0, "fmt": null, "longFmt": "0"}, "downLast90days": {}, "epsRevisionsCurrency": "USD"}}], "defaultMethodology": "nongaap", "maxAge": 1}, "earningsHistory": {"history": [{"maxAge": 1, "epsActual": {"raw": 0.22, "fmt": "0.22"}, "epsEstimate": {"raw": 0.1575, "fmt": "0.16"}, "epsDifference": {"raw": 0.06, "fmt": "0.06"}, "surprisePercent": {"raw": 0.3968, "fmt": "39.68%"}, "quarter": {"raw": 1727654400, "fmt": "2024-09-30"}, "currency": "USD", "period": "-4q"}, {"maxAge": 1, "epsActual": {"raw": 0.2, "fmt": "0.2"}, "epsEstimate": {"raw": 0.195, "fmt": "0.19"}, "epsDifference": {"raw": 0.01, "fmt": "0.01"}, "surprisePercent": {"raw": 0.0256, "fmt": "2.56%"}, "quarter": {"raw": 1735603200, "fmt": "2024-12-31"}, "currency": "USD", "period": "-3q"}, {"maxAge": 1, "epsActual": {"raw": 0.21, "fmt": "0.21"}, "epsEstimate": {"raw": 0.20333, "fmt": "0.2"}, "epsDifference": {"raw": 0.01, "fmt": "0.01"}, "surprisePercent": {"raw": 0.0328, "fmt": "3.28%"}, "quarter": {"raw": 1743379200, "fmt": "2025-03-31"}, "currency": "USD", "period": "-2q"}, {"maxAge": 1, "epsActual": {"raw": 0.25, "fmt": "0.25"}, "epsEstimate": {"raw": 0.246, "fmt": "0.25"}, "epsDifference": {"raw": 0.0, "fmt": "0"}, "surprisePercent": {"raw": 0.0163, "fmt": "1.63%"}, "quarter": {"raw": 1751241600, "fmt": "2025-06-30"}, "currency": "USD", "period": "-1q"}], "defaultMethodology": "nongaap", "maxAge": 86400}, "financialData": {"maxAge": 86400, "currentPrice": {"raw": 15.04, "fmt": "15.04"}, "targetHighPrice": {"raw": 25.0, "fmt": "25.00"}, "targetLowPrice": {"raw": 18.0, "fmt": "18.00"}, "targetMeanPrice": {"raw": 21.75, "fmt": "21.75"}, "targetMedianPrice": {"raw": 22.0, "fmt": "22.00"}, "recommendationMean": {"raw": 1.6, "fmt": "1.60"}, "recommendationKey": "buy", "numberOfAnalystOpinions": {"raw": 4, "fmt": "4", "longFmt": "4"}, "totalCash": {"raw": 110318000, "fmt": "110.32M", "longFmt": "110,318,000"}, "totalCashPerShare": {"raw": 1.913, "fmt": "1.91"}, "ebitda": {"raw": 35993000, "fmt": "35.99M", "longFmt": "35,993,000"}, "totalDebt": {"raw": 8545000, "fmt": "8.54M", "longFmt": "8,545,000"}, "quickRatio": {"raw": 1.453, "fmt": "1.45"}, "currentRatio": {"raw": 1.506, "fmt": "1.51"}, "totalRevenue": {"raw": 1093710976, "fmt": "1.09B", "longFmt": "1,093,710,976"}, "debtToEquity": {"raw": 2.891, "fmt": "2.89%"}, "revenuePerShare": {"raw": 19.366, "fmt": "19.37"}, "returnOnAssets": {"raw": 0.0364, "fmt": "3.64%"}, "returnOnEquity": {"raw": 0.02043, "fmt": "2.04%"}, "grossProfits": {"raw": 110871000, "fmt": "110.87M", "longFmt": "110,871,000"}, "freeCashflow": {"raw": 70207376, "fmt": "70.21M", "longFmt": "70,207,376"}, "operatingCashflow": {"raw": 84980000, "fmt": "84.98M", "longFmt": "84,980,000"}, "earningsGrowth": {"raw": 1.426, "fmt": "142.60%"}, "revenueGrowth": {"raw": 0.293, "fmt": "29.30%"}, "grossMargins": {"raw": 0.10137, "fmt": "10.14%"}, "ebitdaMargins": {"raw": 0.03291, "fmt": "3.29%"}, "operatingMargins": {"raw": 0.0336, "fmt": "3.36%"}, "profitMargins": {"raw": 0.0043, "fmt": "0.43%"}, "financialCurrency": "USD"}}