{"assetProfile": {"address1": "265 Turner Drive", "city": "Durango", "state": "CO", "zip": "81303", "country": "United States", "phone": "970 259 0554", "website": "https://www.rmcf.com", "industry": "Confectioners", "industryKey": "confectioners", "industryDisp": "Confectioners", "sector": "Consumer Defensive", "sectorKey": "consumer-defensive", "sectorDisp": "Consumer Defensive", "longBusinessSummary": "Rocky Mountain Chocolate Factory, Inc., together with its subsidiaries, produces and sells confectionery products in the United States. The company offers chocolate candies and other confectionery products, such as clusters, caramels, creams, toffees, mints, truffles, and gourmet caramel apples. It also franchises and licenses retail stores that offers chocolate and other confectionary products. Rocky Mountain Chocolate Factory, Inc. was founded in 1981 and is headquartered in Durango, Colorado.", "fullTimeEmployees": 140, "companyOfficers": [{"maxAge": 1, "name": "Mr. Jeffrey Richart Geygan", "age": 63, "title": "Interim CEO & Director", "yearBorn": 1961, "fiscalYear": 2025, "totalPay": {"raw": 381100, "fmt": "381.1k", "longFmt": "381,100"}, "exercisedValue": {"raw": 0, "fmt": null, "longFmt": "0"}, "unexercisedValue": {"raw": 0, "fmt": null, "longFmt": "0"}}, {"maxAge": 1, "name": "Ms. Carrie E. Cass", "age": 59, "title": "Corporate Secretary & CFO", "yearBorn": 1965, "fiscalYear": 2025, "totalPay": {"raw": 197770, "fmt": "197.77k", "longFmt": "197,770"}, "exercisedValue": {"raw": 0, "fmt": null, "longFmt": "0"}, "unexercisedValue": {"raw": 0, "fmt": null, "longFmt": "0"}}, {"maxAge": 1, "name": "Mr. Luis  Burgos", "title": "Vice President of Operations", "fiscalYear": 2025, "exercisedValue": {"raw": 0, "fmt": null, "longFmt": "0"}, "unexercisedValue": {"raw": 0, "fmt": null, "longFmt": "0"}}], "compensationAsOfEpochDate": 1767139200, "executiveTeam": [], "maxAge": 86400}, "calendarEvents": {"maxAge": 1, "earnings": {"earningsDate": [{"raw": 1768338000, "fmt": "2026-01-13"}], "earningsCallDate": [{"raw": 1760446800, "fmt": "2025-10-14"}], "isEarningsDateEstimate": true, "earningsAverage": {}, "earningsLow": {}, "earningsHigh": {}, "revenueAverage": {}, "revenueLow": {}, "revenueHigh": {}}, "exDividendDate": {"raw": 1582761600, "fmt": "2020-02-27"}, "dividendDate": {"raw": 1634256000, "fmt": "2021-10-15"}}, "earningsTrend": {"trend": [{"maxAge": 1, "period": "0q", "endDate": null, "growth": {}, "earningsEstimate": {"avg": {}, "low": {}, "high": {}, "yearAgoEps": {}, "numberOfAnalysts": {}, "growth": {}, "earningsCurrency": null}, "revenueEstimate": {"avg": {"raw": 0, "fmt": null, "longFmt": "0"}, "low": {"raw": 0, "fmt": null, "longFmt": "0"}, "high": {"raw": 0, "fmt": null, "longFmt": "0"}, "numberOfAnalysts": {"raw": 0, "fmt": null, "longFmt": "0"}, "yearAgoRevenue": {}, "growth": {}, "revenueCurrency": null}, "epsTrend": {"current": {}, "7daysAgo": {}, "30daysAgo": {}, "60daysAgo": {}, "90daysAgo": {}, "epsTrendCurrency": null}, "epsRevisions": {"upLast7days": {}, "upLast30days": {}, "downLast30days": {}, "downLast7Days": {}, "downLast90days": {}, "epsRevisionsCurrency": null}}, {"maxAge": 1, "period": "+1q", "endDate": "2015-05-31", "growth": {}, "earningsEstimate": {"avg": {}, "low": {}, "high": {}, "yearAgoEps": {}, "numberOfAnalysts": {}, "growth": {}, "earningsCurrency": null}, "revenueEstimate": {"avg": {"raw": 0, "fmt": null, "longFmt": "0"}, "low": {"raw": 0, "fmt": null, "longFmt": "0"}, "high": {"raw": 0, "fmt": null, "longFmt": "0"}, "numberOfAnalysts": {"raw": 0, "fmt": null, "longFmt": "0"}, "yearAgoRevenue": {}, "growth": {}, "revenueCurrency": null}, "epsTrend": {"current": {}, "7daysAgo": {}, "30daysAgo": {}, "60daysAgo": {}, "90daysAgo": {}, "epsTrendCurrency": null}, "epsRevisions": {"upLast7days": {}, "upLast30days": {}, "downLast30days": {}, "downLast7Days": {}, "downLast90days": {}, "epsRevisionsCurrency": null}}, {"maxAge": 1, "period": "0y", "endDate": "2015-02-28", "growth": {}, "earningsEstimate": {"avg": {}, "low": {}, "high": {}, "yearAgoEps": {}, "numberOfAnalysts": {}, "growth": {}, "earningsCurrency": null}, "revenueEstimate": {"avg": {"raw": 0, "fmt": null, "longFmt": "0"}, "low": {"raw": 0, "fmt": null, "longFmt": "0"}, "high": {"raw": 0, "fmt": null, "longFmt": "0"}, "numberOfAnalysts": {"raw": 0, "fmt": null, "longFmt": "0"}, "yearAgoRevenue": {}, "growth": {}, "revenueCurrency": null}, "epsTrend": {"current": {}, "7daysAgo": {}, "30daysAgo": {}, "60daysAgo": {}, "90daysAgo": {}, "epsTrendCurrency": null}, "epsRevisions": {"upLast7days": {}, "upLast30days": {}, "downLast30days": {}, "downLast7Days": {}, "downLast90days": {}, "epsRevisionsCurrency": null}}, {"maxAge": 1, "period": "+1y", "endDate": null, "growth": {}, "earningsEstimate": {"avg": {}, "low": {}, "high": {}, "yearAgoEps": {}, "numberOfAnalysts": {}, "growth": {}, "earningsCurrency": null}, "revenueEstimate": {"avg": {"raw": 0, "fmt": null, "longFmt": "0"}, "low": {"raw": 0, "fmt": null, "longFmt": "0"}, "high": {"raw": 0, "fmt": null, "longFmt": "0"}, "numberOfAnalysts": {"raw": 0, "fmt": null, "longFmt": "0"}, "yearAgoRevenue": {}, "growth": {}, "revenueCurrency": null}, "epsTrend": {"current": {}, "7daysAgo": {}, "30daysAgo": {}, "60daysAgo": {}, "90daysAgo": {}, "epsTrendCurrency": null}, "epsRevisions": {"upLast7days": {}, "upLast30days": {}, "downLast30days": {}, "downLast7Days": {}, "downLast90days": {}, "epsRevisionsCurrency": null}}], "defaultMethodology": "nongaap", "maxAge": 1}, "earningsHistory": {"history": [{"maxAge": 1, "epsActual": {"raw": 0.2557, "fmt": "0.26"}, "epsEstimate": {"raw": 0.17, "fmt": "0.17"}, "epsDifference": {"raw": 0.09, "fmt": "0.09"}, "surprisePercent": {"raw": 0.5041, "fmt": "50.41%"}, "quarter": {"raw": 1393545600, "fmt": "2014-02-28"}, "currency": "USD", "period": "-4q"}, {"maxAge": 1, "epsActual": {"raw": 0.14, "fmt": "0.14"}, "epsEstimate": {"raw": 0.24, "fmt": "0.24"}, "epsDifference": {"raw": -0.1, "fmt": "-0.1"}, "surprisePercent": {"raw": -0.41669998, "fmt": "-41.67%"}, "quarter": {"raw": 1401494400, "fmt": "2014-05-31"}, "currency": "USD", "period": "-3q"}, {"maxAge": 1, "epsActual": {"raw": 0.2, "fmt": "0.2"}, "epsEstimate": {"raw": 0.22, "fmt": "0.22"}, "epsDifference": {"raw": -0.02, "fmt": "-0.02"}, "surprisePercent": {"raw": -0.090900004, "fmt": "-9.09%"}, "quarter": {"raw": 1409443200, "fmt": "2014-08-31"}, "currency": "USD", "period": "-2q"}, {"maxAge": 1, "epsActual": {"raw": 0.15, "fmt": "0.15"}, "epsEstimate": {}, "epsDifference": {}, "surprisePercent": {}, "quarter": {"raw": 1417305600, "fmt": "2014-11-30"}, "currency": "USD", "period": "-1q"}], "defaultMethodology": "nongaap", "maxAge": 86400}, "financialData": {"maxAge": 86400, "currentPrice": {"raw": 1.67, "fmt": "1.67"}, "targetHighPrice": {}, "targetLowPrice": {}, "targetMeanPrice": {}, "targetMedianPrice": {}, "recommendationMean": {}, "recommendationKey": "none", "numberOfAnalystOpinions": {}, "totalCash": {"raw": 2017000, "fmt": "2.02M", "longFmt": "2,017,000"}, "totalCashPerShare": {"raw": 0.259, "fmt": "0.26"}, "ebitda": {"raw": -2848000, "fmt": "-2.85M", "longFmt": "-2,848,000"}, "totalDebt": {"raw": 9443000, "fmt": "9.44M", "longFmt": "9,443,000"}, "quickRatio": {"raw": 0.793, "fmt": "0.79"}, "currentRatio": {"raw": 1.531, "fmt": "1.53"}, "totalRevenue": {"raw": 29988000, "fmt": "29.99M", "longFmt": "29,988,000"}, "debtToEquity": {"raw": 154.146, "fmt": "154.15%"}, "revenuePerShare": {"raw": 3.891, "fmt": "3.89"}, "returnOnAssets": {"raw": -0.115880005, "fmt": "-11.59%"}, "returnOnEquity": {"raw": -0.56789, "fmt": "-56.79%"}, "grossProfits": {"raw": 3576000, "fmt": "3.58M", "longFmt": "3,576,000"}, "freeCashflow": {"raw": -948500, "fmt": "-948.5k", "longFmt": "-948,500"}, "operatingCashflow": {"raw": -1063000, "fmt": "-1.06M", "longFmt": "-1,063,000"}, "earningsGrowth": {}, "revenueGrowth": {"raw": 0.069, "fmt": "6.90%"}, "grossMargins": {"raw": 0.11925, "fmt": "11.92%"}, "ebitdaMargins": {"raw": -0.094969995, "fmt": "-9.50%"}, "operatingMargins": {"raw": -0.070199996, "fmt": "-7.02%"}, "profitMargins": {"raw": -0.15766, "fmt": "-15.77%"}, "financialCurrency": "USD"}}