{"assetProfile": {"address1": "1900 Southeast Loop 820", "city": "Fort Worth", "state": "TX", "zip": "76140", "country": "United States", "phone": "817 872 3200", "website": "https://www.tandyleather.com", "industry": "Specialty Retail", "industryKey": "specialty-retail", "industryDisp": "Specialty Retail", "sector": "Consumer Cyclical", "sectorKey": "consumer-cyclical", "sectorDisp": "Consumer Cyclical", "longBusinessSummary": "Tandy Leather Factory, Inc., together with its subsidiaries, retails leather and leathercraft-related items in the United States, Canada, and Spain. It offers leather, hand tools, hardware, kits, liquids, teaching materials, open workbenches, machines, and other supplies. The company manufactures leather laces, cut leather pieces, do-it-yourself kits, thread laces, belt strips and straps, and Craftaid tooling template through its stores and website, as well as direct account representative. In addition, it offers production services, including cutting, splitting, and assembly services to commercial and business customers. The company sells its products to retail customers, including hobbyists, schools, camps, other businesses, as well as military and first responders under the Tandy Leather, Eco-Flo, Craftool, CraftoolPro, Dr. Jackson's, and TandyPro brand names. The company was formerly known as The Leather Factory, Inc. and changed its name to Tandy Leather Factory, Inc. in 2005. Tandy Leather Factory, Inc. was founded in 1919 and is headquartered in Fort Worth, Texas.", "fullTimeEmployees": 414, "companyOfficers": [{"maxAge": 1, "name": "Mr. Johan  Hedberg M.B.A.", "age": 58, "title": "CEO & Director", "yearBorn": 1966, "exercisedValue": {"raw": 0, "fmt": null, "longFmt": "0"}, "unexercisedValue": {"raw": 0, "fmt": null, "longFmt": "0"}}, {"maxAge": 1, "name": "Mr. Daniel J. Ross J.D.", "age": 54, "title": "General Counsel & Secretary", "yearBorn": 1970, "exercisedValue": {"raw": 0, "fmt": null, "longFmt": "0"}, "unexercisedValue": {"raw": 0, "fmt": null, "longFmt": "0"}}], "irWebsite": "http://www.tandyleatherfactory.com/en-usd/investor_relations.html", "executiveTeam": [], "maxAge": 86400}, "calendarEvents": {"maxAge": 1, "earnings": {"earningsDate": [{"raw": 1754424000, "fmt": "2025-08-05"}, {"raw": 1754942400, "fmt": "2025-08-11"}], "earningsCallDate": [], "isEarningsDateEstimate": true, "earningsAverage": {}, "earningsLow": {}, "earningsHigh": {}, "revenueAverage": {}, "revenueLow": {}, "revenueHigh": {}}, "exDividendDate": {"raw": 1739923200, "fmt": "2025-02-19"}, "dividendDate": {"raw": 1739836800, "fmt": "2025-02-18"}}, "earningsTrend": {"trend": [{"maxAge": 1, "period": "0q", "endDate": null, "growth": {}, "earningsEstimate": {"avg": {}, "low": {}, "high": {}, "yearAgoEps": {}, "numberOfAnalysts": {}, "growth": {}, "earningsCurrency": null}, "revenueEstimate": {"avg": {"raw": 0, "fmt": null, "longFmt": "0"}, "low": {"raw": 0, "fmt": null, "longFmt": "0"}, "high": {"raw": 0, "fmt": null, "longFmt": "0"}, "numberOfAnalysts": {"raw": 0, "fmt": null, "longFmt": "0"}, "yearAgoRevenue": {}, "growth": {}, "revenueCurrency": null}, "epsTrend": {"current": {}, "7daysAgo": {}, "30daysAgo": {}, "60daysAgo": {}, "90daysAgo": {}, "epsTrendCurrency": null}, "epsRevisions": {"upLast7days": {}, "upLast30days": {}, "downLast30days": {}, "downLast7Days": {}, "downLast90days": {}, "epsRevisionsCurrency": null}}, {"maxAge": 1, "period": "+1q", "endDate": "2023-03-31", "growth": {}, "earningsEstimate": {"avg": {}, "low": {}, "high": {}, "yearAgoEps": {}, "numberOfAnalysts": {}, "growth": {}, "earningsCurrency": null}, "revenueEstimate": {"avg": {"raw": 0, "fmt": null, "longFmt": "0"}, "low": {"raw": 0, "fmt": null, "longFmt": "0"}, "high": {"raw": 0, "fmt": null, "longFmt": "0"}, "numberOfAnalysts": {"raw": 0, "fmt": null, "longFmt": "0"}, "yearAgoRevenue": {}, "growth": {}, "revenueCurrency": null}, "epsTrend": {"current": {}, "7daysAgo": {}, "30daysAgo": {}, "60daysAgo": {}, "90daysAgo": {}, "epsTrendCurrency": null}, "epsRevisions": {"upLast7days": {}, "upLast30days": {}, "downLast30days": {}, "downLast7Days": {}, "downLast90days": {}, "epsRevisionsCurrency": null}}, {"maxAge": 1, "period": "0y", "endDate": "2022-12-31", "growth": {}, "earningsEstimate": {"avg": {}, "low": {}, "high": {}, "yearAgoEps": {}, "numberOfAnalysts": {}, "growth": {}, "earningsCurrency": null}, "revenueEstimate": {"avg": {"raw": 0, "fmt": null, "longFmt": "0"}, "low": {"raw": 0, "fmt": null, "longFmt": "0"}, "high": {"raw": 0, "fmt": null, "longFmt": "0"}, "numberOfAnalysts": {"raw": 0, "fmt": null, "longFmt": "0"}, "yearAgoRevenue": {}, "growth": {}, "revenueCurrency": null}, "epsTrend": {"current": {}, "7daysAgo": {}, "30daysAgo": {}, "60daysAgo": {}, "90daysAgo": {}, "epsTrendCurrency": null}, "epsRevisions": {"upLast7days": {}, "upLast30days": {}, "downLast30days": {}, "downLast7Days": {}, "downLast90days": {}, "epsRevisionsCurrency": null}}, {"maxAge": 1, "period": "+1y", "endDate": null, "growth": {}, "earningsEstimate": {"avg": {}, "low": {}, "high": {}, "yearAgoEps": {}, "numberOfAnalysts": {}, "growth": {}, "earningsCurrency": null}, "revenueEstimate": {"avg": {"raw": 0, "fmt": null, "longFmt": "0"}, "low": {"raw": 0, "fmt": null, "longFmt": "0"}, "high": {"raw": 0, "fmt": null, "longFmt": "0"}, "numberOfAnalysts": {"raw": 0, "fmt": null, "longFmt": "0"}, "yearAgoRevenue": {}, "growth": {}, "revenueCurrency": null}, "epsTrend": {"current": {}, "7daysAgo": {}, "30daysAgo": {}, "60daysAgo": {}, "90daysAgo": {}, "epsTrendCurrency": null}, "epsRevisions": {"upLast7days": {}, "upLast30days": {}, "downLast30days": {}, "downLast7Days": {}, "downLast90days": {}, "epsRevisionsCurrency": null}}], "defaultMethodology": "nongaap", "maxAge": 1}, "earningsHistory": {"history": [{"maxAge": 1, "epsActual": {"raw": 0.01, "fmt": "0.01"}, "epsEstimate": {"raw": 0.11, "fmt": "0.11"}, "epsDifference": {"raw": -0.1, "fmt": "-0.1"}, "surprisePercent": {"raw": -0.90910006, "fmt": "-90.91%"}, "quarter": {"raw": 1640908800, "fmt": "2021-12-31"}, "currency": "USD", "period": "-4q"}, {"maxAge": 1, "epsActual": {"raw": 0.08, "fmt": "0.08"}, "epsEstimate": {"raw": 0.06, "fmt": "0.06"}, "epsDifference": {"raw": 0.02, "fmt": "0.02"}, "surprisePercent": {"raw": 0.33330002, "fmt": "33.33%"}, "quarter": {"raw": 1648684800, "fmt": "2022-03-31"}, "currency": "USD", "period": "-3q"}, {"maxAge": 1, "epsActual": {"raw": -0.07, "fmt": "-0.07"}, "epsEstimate": {"raw": 0.08, "fmt": "0.08"}, "epsDifference": {"raw": -0.15, "fmt": "-0.15"}, "surprisePercent": {"raw": -1.875, "fmt": "-187.50%"}, "quarter": {"raw": 1656547200, "fmt": "2022-06-30"}, "currency": "USD", "period": "-2q"}, {"maxAge": 1, "epsActual": {"raw": 0.09, "fmt": "0.09"}, "epsEstimate": {"raw": -0.08, "fmt": "-0.08"}, "epsDifference": {"raw": 0.17, "fmt": "0.17"}, "surprisePercent": {"raw": 2.125, "fmt": "212.50%"}, "quarter": {"raw": 1664496000, "fmt": "2022-09-30"}, "currency": "USD", "period": "-1q"}], "defaultMethodology": "nongaap", "maxAge": 86400}, "financialData": {"maxAge": 86400, "currentPrice": {"raw": 3.06, "fmt": "3.06"}, "targetHighPrice": {}, "targetLowPrice": {}, "targetMeanPrice": {}, "targetMedianPrice": {}, "recommendationMean": {}, "recommendationKey": "none", "numberOfAnalystOpinions": {}, "totalCash": {"raw": 16419000, "fmt": "16.42M", "longFmt": "16,419,000"}, "totalCashPerShare": {"raw": 2.035, "fmt": "2.04"}, "ebitda": {"raw": 1176000, "fmt": "1.18M", "longFmt": "1,176,000"}, "totalDebt": {"raw": 11415000, "fmt": "11.41M", "longFmt": "11,415,000"}, "quickRatio": {"raw": 1.545, "fmt": "1.54"}, "currentRatio": {"raw": 4.889, "fmt": "4.89"}, "totalRevenue": {"raw": 74639000, "fmt": "74.64M", "longFmt": "74,639,000"}, "debtToEquity": {"raw": 19.948, "fmt": "19.95%"}, "revenuePerShare": {"raw": 8.74, "fmt": "8.74"}, "returnOnAssets": {"raw": 0.00204, "fmt": "0.20%"}, "returnOnEquity": {"raw": 0.22094999, "fmt": "22.09%"}, "grossProfits": {"raw": 42157000, "fmt": "42.16M", "longFmt": "42,157,000"}, "freeCashflow": {"raw": 3516500, "fmt": "3.52M", "longFmt": "3,516,500"}, "operatingCashflow": {"raw": -525000, "fmt": "-525k", "longFmt": "-525,000"}, "earningsGrowth": {}, "revenueGrowth": {"raw": 0.028, "fmt": "2.80%"}, "grossMargins": {"raw": 0.56481, "fmt": "56.48%"}, "ebitdaMargins": {"raw": 0.015759999, "fmt": "1.58%"}, "operatingMargins": {"raw": 0.0037099998, "fmt": "0.37%"}, "profitMargins": {"raw": 0.16986, "fmt": "16.99%"}, "financialCurrency": "USD"}}