{"assetProfile": {"address1": "Gushan Standard Factory Building Project", "address2": "Ganzhou New Energy Vehicle Technology City located at West Gushan Road and North Xingguang Ro", "city": "Ganzhou", "zip": "341000", "country": "China", "website": "https://www.elongpower.com", "industry": "Electrical Equipment & Parts", "industryKey": "electrical-equipment-parts", "industryDisp": "Electrical Equipment & Parts", "sector": "Industrials", "sectorKey": "industrials", "sectorDisp": "Industrials", "longBusinessSummary": "Elong Power Holding Limited research, develops, produces, and markets application of high-power lithium-ion battery packs, cells, and parts for electric vehicles and construction machinery. It also offers lithium-ion batteries for energy storage systems. In addition, the company provides battery cells, modules, system integration, and battery management system. Further, it is involved in the research, development, manufacture, and sale of backup power supplies, energy storage systems, and accessories. The company was founded in 2014 and is based in Ganzhou, China.", "fullTimeEmployees": 38, "companyOfficers": [{"maxAge": 1, "name": "Ms. Xiaodan  Liu", "age": 45, "title": "CEO & Chairwoman of Board", "yearBorn": 1979, "exercisedValue": {"raw": 0, "fmt": null, "longFmt": "0"}, "unexercisedValue": {"raw": 0, "fmt": null, "longFmt": "0"}}, {"maxAge": 1, "name": "Mr. Wei  Zou", "age": 54, "title": "Chief Financial Officer", "yearBorn": 1970, "exercisedValue": {"raw": 0, "fmt": null, "longFmt": "0"}, "unexercisedValue": {"raw": 0, "fmt": null, "longFmt": "0"}}, {"maxAge": 1, "name": "Ms. Luyi  Wang", "age": 29, "title": "Compliance Officer", "yearBorn": 1995, "exercisedValue": {"raw": 0, "fmt": null, "longFmt": "0"}, "unexercisedValue": {"raw": 0, "fmt": null, "longFmt": "0"}}, {"maxAge": 1, "name": "Mr. Zhaohui  Yang", "age": 58, "title": "Executive Director", "yearBorn": 1966, "exercisedValue": {"raw": 0, "fmt": null, "longFmt": "0"}, "unexercisedValue": {"raw": 0, "fmt": null, "longFmt": "0"}}], "executiveTeam": [], "maxAge": 86400}, "calendarEvents": {"maxAge": 1, "earnings": {"earningsDate": [], "earningsCallDate": [], "earningsAverage": {}, "earningsLow": {}, "earningsHigh": {}, "revenueAverage": {}, "revenueLow": {}, "revenueHigh": {}}, "exDividendDate": {}, "dividendDate": {}}, "earningsTrend": {"trend": [{"maxAge": 1, "period": "0q", "endDate": null, "growth": {}, "earningsEstimate": {"avg": {}, "low": {}, "high": {}, "yearAgoEps": {}, "numberOfAnalysts": {}, "growth": {}, "earningsCurrency": null}, "revenueEstimate": {"avg": {"raw": 0, "fmt": null, "longFmt": "0"}, "low": {"raw": 0, "fmt": null, "longFmt": "0"}, "high": {"raw": 0, "fmt": null, "longFmt": "0"}, "numberOfAnalysts": {"raw": 0, "fmt": null, "longFmt": "0"}, "yearAgoRevenue": {}, "growth": {}, "revenueCurrency": null}, "epsTrend": {"current": {}, "7daysAgo": {}, "30daysAgo": {}, "60daysAgo": {}, "90daysAgo": {}, "epsTrendCurrency": null}, "epsRevisions": {"upLast7days": {}, "upLast30days": {}, "downLast30days": {}, "downLast7Days": {}, "downLast90days": {}, "epsRevisionsCurrency": null}}, {"maxAge": 1, "period": "+1q", "endDate": null, "growth": {}, "earningsEstimate": {"avg": {}, "low": {}, "high": {}, "yearAgoEps": {}, "numberOfAnalysts": {}, "growth": {}, "earningsCurrency": null}, "revenueEstimate": {"avg": {"raw": 0, "fmt": null, "longFmt": "0"}, "low": {"raw": 0, "fmt": null, "longFmt": "0"}, "high": {"raw": 0, "fmt": null, "longFmt": "0"}, "numberOfAnalysts": {"raw": 0, "fmt": null, "longFmt": "0"}, "yearAgoRevenue": {}, "growth": {}, "revenueCurrency": null}, "epsTrend": {"current": {}, "7daysAgo": {}, "30daysAgo": {}, "60daysAgo": {}, "90daysAgo": {}, "epsTrendCurrency": null}, "epsRevisions": {"upLast7days": {}, "upLast30days": {}, "downLast30days": {}, "downLast7Days": {}, "downLast90days": {}, "epsRevisionsCurrency": null}}, {"maxAge": 1, "period": "0y", "endDate": null, "growth": {}, "earningsEstimate": {"avg": {}, "low": {}, "high": {}, "yearAgoEps": {}, "numberOfAnalysts": {}, "growth": {}, "earningsCurrency": null}, "revenueEstimate": {"avg": {"raw": 0, "fmt": null, "longFmt": "0"}, "low": {"raw": 0, "fmt": null, "longFmt": "0"}, "high": {"raw": 0, "fmt": null, "longFmt": "0"}, "numberOfAnalysts": {"raw": 0, "fmt": null, "longFmt": "0"}, "yearAgoRevenue": {}, "growth": {}, "revenueCurrency": null}, "epsTrend": {"current": {}, "7daysAgo": {}, "30daysAgo": {}, "60daysAgo": {}, "90daysAgo": {}, "epsTrendCurrency": null}, "epsRevisions": {"upLast7days": {}, "upLast30days": {}, "downLast30days": {}, "downLast7Days": {}, "downLast90days": {}, "epsRevisionsCurrency": null}}, {"maxAge": 1, "period": "+1y", "endDate": null, "growth": {}, "earningsEstimate": {"avg": {}, "low": {}, "high": {}, "yearAgoEps": {}, "numberOfAnalysts": {}, "growth": {}, "earningsCurrency": null}, "revenueEstimate": {"avg": {"raw": 0, "fmt": null, "longFmt": "0"}, "low": {"raw": 0, "fmt": null, "longFmt": "0"}, "high": {"raw": 0, "fmt": null, "longFmt": "0"}, "numberOfAnalysts": {"raw": 0, "fmt": null, "longFmt": "0"}, "yearAgoRevenue": {}, "growth": {}, "revenueCurrency": null}, "epsTrend": {"current": {}, "7daysAgo": {}, "30daysAgo": {}, "60daysAgo": {}, "90daysAgo": {}, "epsTrendCurrency": null}, "epsRevisions": {"upLast7days": {}, "upLast30days": {}, "downLast30days": {}, "downLast7Days": {}, "downLast90days": {}, "epsRevisionsCurrency": null}}], "defaultMethodology": "nongaap", "maxAge": 1}, "earningsHistory": {"history": [], "defaultMethodology": "nongaap", "maxAge": 86400}, "financialData": {"maxAge": 86400, "currentPrice": {"raw": 0.2997, "fmt": "0.30"}, "targetHighPrice": {}, "targetLowPrice": {}, "targetMeanPrice": {}, "targetMedianPrice": {}, "recommendationMean": {}, "recommendationKey": "none", "numberOfAnalystOpinions": {}, "totalCash": {"raw": 7235681, "fmt": "7.24M", "longFmt": "7,235,681"}, "totalCashPerShare": {"raw": 0.123, "fmt": "0.12"}, "ebitda": {"raw": -17058200, "fmt": "-17.06M", "longFmt": "-17,058,200"}, "totalDebt": {"raw": 29734970, "fmt": "29.73M", "longFmt": "29,734,970"}, "quickRatio": {"raw": 0.412, "fmt": "0.41"}, "currentRatio": {"raw": 0.514, "fmt": "0.51"}, "totalRevenue": {"raw": 386940, "fmt": "386.94k", "longFmt": "386,940"}, "debtToEquity": {}, "revenuePerShare": {"raw": 0.007, "fmt": "0.01"}, "returnOnAssets": {"raw": -0.36586, "fmt": "-36.59%"}, "returnOnEquity": {}, "grossProfits": {"raw": -3462291, "fmt": "-3.46M", "longFmt": "-3,462,291"}, "freeCashflow": {"raw": -4480984, "fmt": "-4.48M", "longFmt": "-4,480,984"}, "operatingCashflow": {"raw": -2823640, "fmt": "-2.82M", "longFmt": "-2,823,640"}, "earningsGrowth": {}, "revenueGrowth": {"raw": -0.98, "fmt": "-98.00%"}, "grossMargins": {"raw": 0.0, "fmt": "0.00%"}, "ebitdaMargins": {"raw": 0.0, "fmt": "0.00%"}, "operatingMargins": {"raw": -719.4459, "fmt": "-71,944.59%"}, "profitMargins": {"raw": 0.0, "fmt": "0.00%"}, "financialCurrency": "USD"}}