{"assetProfile": {"address1": "148-150, Boulevard de la PEtrusse", "city": "Luxembourg", "zip": "2330", "country": "Luxembourg", "phone": "352 27 759 021", "website": "https://www.millicom.com", "industry": "Telecom Services", "industryKey": "telecom-services", "industryDisp": "Telecom Services", "sector": "Communication Services", "sectorKey": "communication-services", "sectorDisp": "Communication Services", "longBusinessSummary": "Millicom International Cellular S.A. provides cable and mobile services in Latin America. It offers mobile services, including mobile data and voice, and short message services; and mobile financial services, such as payments, money transfers, international remittances, savings, real-time loans, and micro-insurance. The company also operates TIGO Sports for sports dedicated broadcast business; Tigo Money that allows its customers to send and receive money without the need for a bank account; and TIGO ONEtv for pay TV. In addition, it provides fixed services, including broadband, fixed voice, and pay-TV; and fixed-voice and data telecommunications services, managed services, cloud and security solutions, and value-added services; and tower infrastructure and services. The company serves small, medium, and large businesses, as well as residential consumers and governmental entities. It markets its products and services under the Tigo and Tigo Business brands. The company was founded in 1990 and is headquartered in Luxembourg, Luxembourg.", "fullTimeEmployees": 14000, "companyOfficers": [{"maxAge": 1, "name": "Mr. Marcelo  Benitez", "title": "Chief Executive Officer", "exercisedValue": {"raw": 0, "fmt": null, "longFmt": "0"}, "unexercisedValue": {"raw": 0, "fmt": null, "longFmt": "0"}}, {"maxAge": 1, "name": "Mr. Bart  Vanhaeren", "title": "Chief Financial Officer", "exercisedValue": {"raw": 0, "fmt": null, "longFmt": "0"}, "unexercisedValue": {"raw": 0, "fmt": null, "longFmt": "0"}}, {"maxAge": 1, "name": "Mr. Guillaume  Duhaze", "title": "Chief Technology & Information Officer", "exercisedValue": {"raw": 0, "fmt": null, "longFmt": "0"}, "unexercisedValue": {"raw": 0, "fmt": null, "longFmt": "0"}}, {"maxAge": 1, "name": "Mr. Michel  Morin CFA", "title": "Vice President of Investor Relations", "exercisedValue": {"raw": 0, "fmt": null, "longFmt": "0"}, "unexercisedValue": {"raw": 0, "fmt": null, "longFmt": "0"}}, {"maxAge": 1, "name": "Mr. Salvador  Escalon J.D.", "age": 49, "title": "Executive VP and Chief Legal & Compliance Officer", "yearBorn": 1975, "exercisedValue": {"raw": 0, "fmt": null, "longFmt": "0"}, "unexercisedValue": {"raw": 0, "fmt": null, "longFmt": "0"}}, {"maxAge": 1, "name": "Sofia  Corral", "title": "Director of Corporate Communications", "exercisedValue": {"raw": 0, "fmt": null, "longFmt": "0"}, "unexercisedValue": {"raw": 0, "fmt": null, "longFmt": "0"}}, {"maxAge": 1, "name": "Mr. Karim  Lesina", "age": 49, "title": "Executive VP & Chief External Affairs Officer", "yearBorn": 1975, "exercisedValue": {"raw": 0, "fmt": null, "longFmt": "0"}, "unexercisedValue": {"raw": 0, "fmt": null, "longFmt": "0"}}], "auditRisk": 1, "boardRisk": 6, "compensationRisk": 4, "shareHolderRightsRisk": 3, "overallRisk": 4, "governanceEpochDate": 1761955200, "irWebsite": "http://www.millicom.com/investor_relations/index.php", "executiveTeam": [], "maxAge": 86400}, "calendarEvents": {"maxAge": 1, "earnings": {"earningsDate": [{"raw": 1762435800, "fmt": "2025-11-06"}], "earningsCallDate": [{"raw": 1762434000, "fmt": "2025-11-06"}], "isEarningsDateEstimate": false, "earningsAverage": {"raw": 0.77899, "fmt": "0.78"}, "earningsLow": {"raw": 0.77899, "fmt": "0.78"}, "earningsHigh": {"raw": 0.77899, "fmt": "0.78"}, "revenueAverage": {"raw": 1401948920, "fmt": "1.4B", "longFmt": "1,401,948,920"}, "revenueLow": {"raw": 1395000000, "fmt": "1.4B", "longFmt": "1,395,000,000"}, "revenueHigh": {"raw": 1405846750, "fmt": "1.41B", "longFmt": "1,405,846,750"}}, "exDividendDate": {"raw": 1767830400, "fmt": "2026-01-08"}, "dividendDate": {"raw": 1776211200, "fmt": "2026-04-15"}}, "earningsTrend": {"trend": [{"maxAge": 1, "period": "0q", "endDate": "2025-09-30", "growth": {"raw": 1.5966, "fmt": "159.66%"}, "earningsEstimate": {"avg": {"raw": 0.77899, "fmt": "0.78"}, "low": {"raw": 0.77899, "fmt": "0.78"}, "high": {"raw": 0.77899, "fmt": "0.78"}, "yearAgoEps": {"raw": 0.3, "fmt": "0.3"}, "numberOfAnalysts": {"raw": 1, "fmt": "1", "longFmt": "1"}, "growth": {"raw": 1.5966, "fmt": "159.66%"}, "earningsCurrency": "USD"}, "revenueEstimate": {"avg": {"raw": 1401948920, "fmt": "1.4B", "longFmt": "1,401,948,920"}, "low": {"raw": 1395000000, "fmt": "1.4B", "longFmt": "1,395,000,000"}, "high": {"raw": 1405846750, "fmt": "1.41B", "longFmt": "1,405,846,750"}, "numberOfAnalysts": {"raw": 3, "fmt": "3", "longFmt": "3"}, "yearAgoRevenue": {"raw": 1431000000, "fmt": "1.43B", "longFmt": "1,431,000,000"}, "growth": {"raw": -0.020299999, "fmt": "-2.03%"}, "revenueCurrency": "USD"}, "epsTrend": {"current": {"raw": 0.77899, "fmt": "0.78"}, "7daysAgo": {"raw": 0.0, "fmt": "0"}, "30daysAgo": {"raw": 0.66817, "fmt": "0.67"}, "60daysAgo": {"raw": 0.66791, "fmt": "0.67"}, "90daysAgo": {"raw": 0.66791, "fmt": "0.67"}, "epsTrendCurrency": "USD"}, "epsRevisions": {"upLast7days": {"raw": 0, "fmt": null, "longFmt": "0"}, "upLast30days": {"raw": 0, "fmt": null, "longFmt": "0"}, "downLast30days": {"raw": 1, "fmt": "1", "longFmt": "1"}, "downLast7Days": {"raw": 0, "fmt": null, "longFmt": "0"}, "downLast90days": {}, "epsRevisionsCurrency": "USD"}}, {"maxAge": 1, "period": "+1q", "endDate": "2025-12-31", "growth": {"raw": 2.4713001, "fmt": "247.13%"}, "earningsEstimate": {"avg": {"raw": 0.89975, "fmt": "0.9"}, "low": {"raw": 0.89975, "fmt": "0.9"}, "high": {"raw": 0.89975, "fmt": "0.9"}, "yearAgoEps": {"raw": 0.2592, "fmt": "0.26"}, "numberOfAnalysts": {"raw": 1, "fmt": "1", "longFmt": "1"}, "growth": {"raw": 2.4713001, "fmt": "247.13%"}, "earningsCurrency": "USD"}, "revenueEstimate": {"avg": {"raw": 1426392130, "fmt": "1.43B", "longFmt": "1,426,392,130"}, "low": {"raw": 1412000000, "fmt": "1.41B", "longFmt": "1,412,000,000"}, "high": {"raw": 1442000000, "fmt": "1.44B", "longFmt": "1,442,000,000"}, "numberOfAnalysts": {"raw": 3, "fmt": "3", "longFmt": "3"}, "yearAgoRevenue": {"raw": 1428000000, "fmt": "1.43B", "longFmt": "1,428,000,000"}, "growth": {"raw": -0.0011, "fmt": "-0.11%"}, "revenueCurrency": "USD"}, "epsTrend": {"current": {"raw": 0.89975, "fmt": "0.9"}, "7daysAgo": {"raw": 0.0, "fmt": "0"}, "30daysAgo": {"raw": 0.719, "fmt": "0.72"}, "60daysAgo": {"raw": 0.71744, "fmt": "0.72"}, "90daysAgo": {"raw": 0.71744, "fmt": "0.72"}, "epsTrendCurrency": "USD"}, "epsRevisions": {"upLast7days": {"raw": 0, "fmt": null, "longFmt": "0"}, "upLast30days": {"raw": 1, "fmt": "1", "longFmt": "1"}, "downLast30days": {"raw": 0, "fmt": null, "longFmt": "0"}, "downLast7Days": {"raw": 0, "fmt": null, "longFmt": "0"}, "downLast90days": {}, "epsRevisionsCurrency": "USD"}}, {"maxAge": 1, "period": "0y", "endDate": "2025-12-31", "growth": {"raw": 0.4082, "fmt": "40.82%"}, "earningsEstimate": {"avg": {"raw": 2.70525, "fmt": "2.71"}, "low": {"raw": 2.49, "fmt": "2.49"}, "high": {"raw": 2.9802, "fmt": "2.98"}, "yearAgoEps": {"raw": 1.9211, "fmt": "1.92"}, "numberOfAnalysts": {"raw": 4, "fmt": "4", "longFmt": "4"}, "growth": {"raw": 0.4082, "fmt": "40.82%"}, "earningsCurrency": "USD"}, "revenueEstimate": {"avg": {"raw": 5592142960, "fmt": "5.59B", "longFmt": "5,592,142,960"}, "low": {"raw": 5539000000, "fmt": "5.54B", "longFmt": "5,539,000,000"}, "high": {"raw": 5755000000, "fmt": "5.75B", "longFmt": "5,755,000,000"}, "numberOfAnalysts": {"raw": 8, "fmt": "8", "longFmt": "8"}, "yearAgoRevenue": {"raw": 5804000000, "fmt": "5.8B", "longFmt": "5,804,000,000"}, "growth": {"raw": -0.0365, "fmt": "-3.65%"}, "revenueCurrency": "USD"}, "epsTrend": {"current": {"raw": 2.70525, "fmt": "2.71"}, "7daysAgo": {"raw": 2.70525, "fmt": "2.71"}, "30daysAgo": {"raw": 2.77562, "fmt": "2.78"}, "60daysAgo": {"raw": 2.77562, "fmt": "2.78"}, "90daysAgo": {"raw": 2.9106, "fmt": "2.91"}, "epsTrendCurrency": "USD"}, "epsRevisions": {"upLast7days": {"raw": 0, "fmt": null, "longFmt": "0"}, "upLast30days": {"raw": 0, "fmt": null, "longFmt": "0"}, "downLast30days": {"raw": 0, "fmt": null, "longFmt": "0"}, "downLast7Days": {"raw": 0, "fmt": null, "longFmt": "0"}, "downLast90days": {}, "epsRevisionsCurrency": "USD"}}, {"maxAge": 1, "period": "+1y", "endDate": "2026-12-31", "growth": {"raw": 0.3436, "fmt": "34.36%"}, "earningsEstimate": {"avg": {"raw": 3.6348, "fmt": "3.63"}, "low": {"raw": 2.95, "fmt": "2.95"}, "high": {"raw": 4.0756, "fmt": "4.08"}, "yearAgoEps": {"raw": 2.70525, "fmt": "2.71"}, "numberOfAnalysts": {"raw": 5, "fmt": "5", "longFmt": "5"}, "growth": {"raw": 0.3436, "fmt": "34.36%"}, "earningsCurrency": "USD"}, "revenueEstimate": {"avg": {"raw": 5951495350, "fmt": "5.95B", "longFmt": "5,951,495,350"}, "low": {"raw": 5603000000, "fmt": "5.6B", "longFmt": "5,603,000,000"}, "high": {"raw": 7572000000, "fmt": "7.57B", "longFmt": "7,572,000,000"}, "numberOfAnalysts": {"raw": 9, "fmt": "9", "longFmt": "9"}, "yearAgoRevenue": {"raw": 5592142960, "fmt": "5.59B", "longFmt": "5,592,142,960"}, "growth": {"raw": 0.0643, "fmt": "6.43%"}, "revenueCurrency": "USD"}, "epsTrend": {"current": {"raw": 3.6348, "fmt": "3.63"}, "7daysAgo": {"raw": 3.6348, "fmt": "3.63"}, "30daysAgo": {"raw": 3.6191, "fmt": "3.62"}, "60daysAgo": {"raw": 3.5167, "fmt": "3.52"}, "90daysAgo": {"raw": 3.65306, "fmt": "3.65"}, "epsTrendCurrency": "USD"}, "epsRevisions": {"upLast7days": {"raw": 1, "fmt": "1", "longFmt": "1"}, "upLast30days": {"raw": 2, "fmt": "2", "longFmt": "2"}, "downLast30days": {"raw": 0, "fmt": null, "longFmt": "0"}, "downLast7Days": {"raw": 0, "fmt": null, "longFmt": "0"}, "downLast90days": {}, "epsRevisionsCurrency": "USD"}}], "defaultMethodology": "nongaap", "maxAge": 1}, "earningsHistory": {"history": [{"maxAge": 1, "epsActual": {"raw": 0.3, "fmt": "0.3"}, "epsEstimate": {"raw": 0.62456, "fmt": "0.62"}, "epsDifference": {"raw": -0.32, "fmt": "-0.32"}, "surprisePercent": {"raw": -0.5197, "fmt": "-51.97%"}, "quarter": {"raw": 1727654400, "fmt": "2024-09-30"}, "currency": "USD", "period": "-4q"}, {"maxAge": 1, "epsActual": {"raw": 0.2592, "fmt": "0.26"}, "epsEstimate": {"raw": 0.70172, "fmt": "0.7"}, "epsDifference": {"raw": -0.44, "fmt": "-0.44"}, "surprisePercent": {"raw": -0.63060004, "fmt": "-63.06%"}, "quarter": {"raw": 1735603200, "fmt": "2024-12-31"}, "currency": "USD", "period": "-3q"}, {"maxAge": 1, "epsActual": {"raw": 1.14, "fmt": "1.14"}, "epsEstimate": {"raw": 0.80203, "fmt": "0.8"}, "epsDifference": {"raw": 0.34, "fmt": "0.34"}, "surprisePercent": {"raw": 0.42139998, "fmt": "42.14%"}, "quarter": {"raw": 1743379200, "fmt": "2025-03-31"}, "currency": "USD", "period": "-2q"}, {"maxAge": 1, "epsActual": {"raw": 0.9044, "fmt": "0.9"}, "epsEstimate": {"raw": 0.64193, "fmt": "0.64"}, "epsDifference": {"raw": 0.26, "fmt": "0.26"}, "surprisePercent": {"raw": 0.4089, "fmt": "40.89%"}, "quarter": {"raw": 1751241600, "fmt": "2025-06-30"}, "currency": "USD", "period": "-1q"}], "defaultMethodology": "nongaap", "maxAge": 86400}, "financialData": {"maxAge": 86400, "currentPrice": {"raw": 46.41, "fmt": "46.41"}, "targetHighPrice": {"raw": 55.0, "fmt": "55.00"}, "targetLowPrice": {"raw": 44.0, "fmt": "44.00"}, "targetMeanPrice": {"raw": 49.1375, "fmt": "49.14"}, "targetMedianPrice": {"raw": 48.5, "fmt": "48.50"}, "recommendationMean": {}, "recommendationKey": "none", "numberOfAnalystOpinions": {"raw": 8, "fmt": "8", "longFmt": "8"}, "totalCash": {"raw": 1283000064, "fmt": "1.28B", "longFmt": "1,283,000,064"}, "totalCashPerShare": {"raw": 7.681, "fmt": "7.68"}, "ebitda": {"raw": 2428999936, "fmt": "2.43B", "longFmt": "2,428,999,936"}, "totalDebt": {"raw": 7953999872, "fmt": "7.95B", "longFmt": "7,953,999,872"}, "quickRatio": {"raw": 0.606, "fmt": "0.61"}, "currentRatio": {"raw": 0.889, "fmt": "0.89"}, "totalRevenue": {"raw": 5605000192, "fmt": "5.61B", "longFmt": "5,605,000,192"}, "debtToEquity": {"raw": 227.387, "fmt": "227.39%"}, "revenuePerShare": {"raw": 33.033, "fmt": "33.03"}, "returnOnAssets": {"raw": 0.06179, "fmt": "6.18%"}, "returnOnEquity": {"raw": 0.28265, "fmt": "28.26%"}, "grossProfits": {"raw": 4288999936, "fmt": "4.29B", "longFmt": "4,288,999,936"}, "freeCashflow": {"raw": 1617250048, "fmt": "1.62B", "longFmt": "1,617,250,048"}, "operatingCashflow": {"raw": 1680999936, "fmt": "1.68B", "longFmt": "1,680,999,936"}, "earningsGrowth": {"raw": 7.956, "fmt": "795.60%"}, "revenueGrowth": {"raw": -0.059, "fmt": "-5.90%"}, "grossMargins": {"raw": 0.76521003, "fmt": "76.52%"}, "ebitdaMargins": {"raw": 0.43335998, "fmt": "43.34%"}, "operatingMargins": {"raw": 0.25, "fmt": "25.00%"}, "profitMargins": {"raw": 0.16985, "fmt": "16.99%"}, "financialCurrency": "USD"}}