{"assetProfile": {"address1": "500 Delaware Avenue", "city": "Wilmington", "state": "DE", "zip": "19801", "country": "United States", "phone": "302 792 6000", "website": "https://www.wsfsbank.com", "industry": "Banks - Regional", "industryKey": "banks-regional", "industryDisp": "Banks - Regional", "sector": "Financial Services", "sectorKey": "financial-services", "sectorDisp": "Financial Services", "longBusinessSummary": "WSFS Financial Corporation operates as the savings and loan holding company for the Wilmington Savings Fund Society, FSB that provides various banking services in the United States. It operates through WSFS Bank, Cash Connect, and Wealth Management segments. It offers various deposit products, including savings accounts, demand deposits, interest-bearing demand deposits, money market deposit accounts, and certificates of deposit, as well as accepts jumbo certificates of deposit from individuals, businesses, and municipalities. The company also provides various loans, which comprise fixed and adjustable rate residential loans; commercial mortgage and commercial loans; commercial construction loans; commercial loans for working capital, financing equipment and real estate acquisitions, business expansion and other business purposes; and consumer credit products, such as home equity loans, home equity lines of credit, automobile loans, unsecured lines of credit, and other secured and unsecured personal installment loans. In addition, it offers insurance products; planning and advisory services, investment management, trust services, and credit and deposit products to individual, corporate and institutional clients; retail securities and insurance brokerage services; mortgage and title services; residential mortgage and refinancing solutions; and leases small equipment and fixed assets, as well as provides financial planning, customized investment strategies, brokerage products, fiduciary, and wealth management services. Further, the company provides ATM vault cash, smart safe, and other cash logistics services; and online reporting and ATM cash management, predictive cash ordering and reconcilement services, armored carrier management, loss protection, and deposit safe cash logistics services, as well as trustee, agency, bankruptcy administration, custodial and commercial domicile services. The company was founded in 1832 and is headquartered in Wilmington, Delaware.", "fullTimeEmployees": 2338, "companyOfficers": [{"maxAge": 1, "name": "Mr. Rodger  Levenson", "age": 63, "title": "Chairman, President & CEO", "yearBorn": 1961, "fiscalYear": 2024, "totalPay": {"raw": 2268126, "fmt": "2.27M", "longFmt": "2,268,126"}, "exercisedValue": {"raw": 0, "fmt": null, "longFmt": "0"}, "unexercisedValue": {"raw": 0, "fmt": null, "longFmt": "0"}}, {"maxAge": 1, "name": "Mr. David  Burg", "age": 50, "title": "Executive VP & CFO", "yearBorn": 1974, "fiscalYear": 2024, "totalPay": {"raw": 970016, "fmt": "970.02k", "longFmt": "970,016"}, "exercisedValue": {"raw": 0, "fmt": null, "longFmt": "0"}, "unexercisedValue": {"raw": 0, "fmt": null, "longFmt": "0"}}, {"maxAge": 1, "name": "Mr. Arthur J. Bacci", "age": 62, "title": "Executive VP & COO", "yearBorn": 1962, "fiscalYear": 2024, "totalPay": {"raw": 1081175, "fmt": "1.08M", "longFmt": "1,081,175"}, "exercisedValue": {"raw": 205006, "fmt": "205.01k", "longFmt": "205,006"}, "unexercisedValue": {"raw": 1004, "fmt": "1k", "longFmt": "1,004"}}, {"maxAge": 1, "name": "Ms. Lisa M. Brubaker", "age": 60, "title": "Executive VP & Chief Human Resources Officer", "yearBorn": 1964, "fiscalYear": 2024, "totalPay": {"raw": 859628, "fmt": "859.63k", "longFmt": "859,628"}, "exercisedValue": {"raw": 0, "fmt": null, "longFmt": "0"}, "unexercisedValue": {"raw": 240776, "fmt": "240.78k", "longFmt": "240,776"}}, {"maxAge": 1, "name": "Ms. Shari A. Kruzinski", "age": 54, "title": "Executive VP & Chief Consumer Banking Officer", "yearBorn": 1970, "fiscalYear": 2024, "totalPay": {"raw": 762987, "fmt": "762.99k", "longFmt": "762,987"}, "exercisedValue": {"raw": 0, "fmt": null, "longFmt": "0"}, "unexercisedValue": {"raw": 0, "fmt": null, "longFmt": "0"}}, {"maxAge": 1, "name": "Mr. Charles K. Mosher CPA", "title": "Senior VP & Chief Accounting Officer", "fiscalYear": 2024, "exercisedValue": {"raw": 0, "fmt": null, "longFmt": "0"}, "unexercisedValue": {"raw": 0, "fmt": null, "longFmt": "0"}}, {"maxAge": 1, "name": "Ms. Shilpa  Kumar", "title": "Senior VP & Head of Corporate Finance", "fiscalYear": 2024, "exercisedValue": {"raw": 0, "fmt": null, "longFmt": "0"}, "unexercisedValue": {"raw": 0, "fmt": null, "longFmt": "0"}}, {"maxAge": 1, "name": "Mr. Allan  Matyger", "title": "Executive VP & Chief Information Officer", "fiscalYear": 2024, "exercisedValue": {"raw": 0, "fmt": null, "longFmt": "0"}, "unexercisedValue": {"raw": 0, "fmt": null, "longFmt": "0"}}, {"maxAge": 1, "name": "Ms. Lisa  Washington", "age": 56, "title": "Senior VP, Secretary & Chief Legal Officer", "yearBorn": 1968, "fiscalYear": 2024, "exercisedValue": {"raw": 0, "fmt": null, "longFmt": "0"}, "unexercisedValue": {"raw": 0, "fmt": null, "longFmt": "0"}}, {"maxAge": 1, "name": "Ms. Lynn  Hobson", "title": "Senior VP & Chief Marketing Officer", "fiscalYear": 2024, "exercisedValue": {"raw": 0, "fmt": null, "longFmt": "0"}, "unexercisedValue": {"raw": 0, "fmt": null, "longFmt": "0"}}], "auditRisk": 3, "boardRisk": 4, "compensationRisk": 1, "shareHolderRightsRisk": 7, "overallRisk": 4, "governanceEpochDate": 1761955200, "compensationAsOfEpochDate": 1735603200, "irWebsite": "http://investors.wsfsbank.com/", "executiveTeam": [], "maxAge": 86400}, "calendarEvents": {"maxAge": 1, "earnings": {"earningsDate": [{"raw": 1769720400, "fmt": "2026-01-29"}], "earningsCallDate": [{"raw": 1761325200, "fmt": "2025-10-24"}], "isEarningsDateEstimate": true, "earningsAverage": {"raw": 1.2325, "fmt": "1.23"}, "earningsLow": {"raw": 1.18, "fmt": "1.18"}, "earningsHigh": {"raw": 1.25, "fmt": "1.25"}, "revenueAverage": {"raw": 268501330, "fmt": "268.5M", "longFmt": "268,501,330"}, "revenueLow": {"raw": 266639000, "fmt": "266.64M", "longFmt": "266,639,000"}, "revenueHigh": {"raw": 269800000, "fmt": "269.8M", "longFmt": "269,800,000"}}, "exDividendDate": {"raw": 1762473600, "fmt": "2025-11-07"}, "dividendDate": {"raw": 1763683200, "fmt": "2025-11-21"}}, "earningsTrend": {"trend": [{"maxAge": 1, "period": "0q", "endDate": "2025-12-31", "growth": {"raw": 0.1104, "fmt": "11.04%"}, "earningsEstimate": {"avg": {"raw": 1.2325, "fmt": "1.23"}, "low": {"raw": 1.18, "fmt": "1.18"}, "high": {"raw": 1.25, "fmt": "1.25"}, "yearAgoEps": {"raw": 1.11, "fmt": "1.11"}, "numberOfAnalysts": {"raw": 4, "fmt": "4", "longFmt": "4"}, "growth": {"raw": 0.1104, "fmt": "11.04%"}, "earningsCurrency": "USD"}, "revenueEstimate": {"avg": {"raw": 268501330, "fmt": "268.5M", "longFmt": "268,501,330"}, "low": {"raw": 266639000, "fmt": "266.64M", "longFmt": "266,639,000"}, "high": {"raw": 269800000, "fmt": "269.8M", "longFmt": "269,800,000"}, "numberOfAnalysts": {"raw": 3, "fmt": "3", "longFmt": "3"}, "yearAgoRevenue": {"raw": 261500000, "fmt": "261.5M", "longFmt": "261,500,000"}, "growth": {"raw": 0.026800001, "fmt": "2.68%"}, "revenueCurrency": "USD"}, "epsTrend": {"current": {"raw": 1.2325, "fmt": "1.23"}, "7daysAgo": {"raw": 1.245, "fmt": "1.25"}, "30daysAgo": {"raw": 1.262, "fmt": "1.26"}, "60daysAgo": {"raw": 1.2525, "fmt": "1.25"}, "90daysAgo": {"raw": 1.2525, "fmt": "1.25"}, "epsTrendCurrency": "USD"}, "epsRevisions": {"upLast7days": {"raw": 0, "fmt": null, "longFmt": "0"}, "upLast30days": {"raw": 1, "fmt": "1", "longFmt": "1"}, "downLast30days": {"raw": 2, "fmt": "2", "longFmt": "2"}, "downLast7Days": {"raw": 1, "fmt": "1", "longFmt": "1"}, "downLast90days": {}, "epsRevisionsCurrency": "USD"}}, {"maxAge": 1, "period": "+1q", "endDate": "2026-03-31", "growth": {"raw": 0.0465, "fmt": "4.65%"}, "earningsEstimate": {"avg": {"raw": 1.1825, "fmt": "1.18"}, "low": {"raw": 1.12, "fmt": "1.12"}, "high": {"raw": 1.24, "fmt": "1.24"}, "yearAgoEps": {"raw": 1.13, "fmt": "1.13"}, "numberOfAnalysts": {"raw": 4, "fmt": "4", "longFmt": "4"}, "growth": {"raw": 0.0465, "fmt": "4.65%"}, "earningsCurrency": "USD"}, "revenueEstimate": {"avg": {"raw": 262758000, "fmt": "262.76M", "longFmt": "262,758,000"}, "low": {"raw": 259366000, "fmt": "259.37M", "longFmt": "259,366,000"}, "high": {"raw": 265908000, "fmt": "265.91M", "longFmt": "265,908,000"}, "numberOfAnalysts": {"raw": 3, "fmt": "3", "longFmt": "3"}, "yearAgoRevenue": {"raw": 256113000, "fmt": "256.11M", "longFmt": "256,113,000"}, "growth": {"raw": 0.025899999, "fmt": "2.59%"}, "revenueCurrency": "USD"}, "epsTrend": {"current": {"raw": 1.1825, "fmt": "1.18"}, "7daysAgo": {"raw": 1.1925, "fmt": "1.19"}, "30daysAgo": {"raw": 1.204, "fmt": "1.2"}, "60daysAgo": {"raw": 1.195, "fmt": "1.2"}, "90daysAgo": {"raw": 1.195, "fmt": "1.2"}, "epsTrendCurrency": "USD"}, "epsRevisions": {"upLast7days": {"raw": 1, "fmt": "1", "longFmt": "1"}, "upLast30days": {"raw": 1, "fmt": "1", "longFmt": "1"}, "downLast30days": {"raw": 0, "fmt": null, "longFmt": "0"}, "downLast7Days": {"raw": 0, "fmt": null, "longFmt": "0"}, "downLast90days": {}, "epsRevisionsCurrency": "USD"}}, {"maxAge": 1, "period": "0y", "endDate": "2025-12-31", "growth": {"raw": 0.142, "fmt": "14.20%"}, "earningsEstimate": {"avg": {"raw": 5.01333, "fmt": "5.01"}, "low": {"raw": 4.95, "fmt": "4.95"}, "high": {"raw": 5.05, "fmt": "5.05"}, "yearAgoEps": {"raw": 4.39, "fmt": "4.39"}, "numberOfAnalysts": {"raw": 3, "fmt": "3", "longFmt": "3"}, "growth": {"raw": 0.142, "fmt": "14.20%"}, "earningsCurrency": "USD"}, "revenueEstimate": {"avg": {"raw": 1064590000, "fmt": "1.06B", "longFmt": "1,064,590,000"}, "low": {"raw": 1062222000, "fmt": "1.06B", "longFmt": "1,062,222,000"}, "high": {"raw": 1066900000, "fmt": "1.07B", "longFmt": "1,066,900,000"}, "numberOfAnalysts": {"raw": 3, "fmt": "3", "longFmt": "3"}, "yearAgoRevenue": {"raw": 1046400000, "fmt": "1.05B", "longFmt": "1,046,400,000"}, "growth": {"raw": 0.0174, "fmt": "1.74%"}, "revenueCurrency": "USD"}, "epsTrend": {"current": {"raw": 5.01333, "fmt": "5.01"}, "7daysAgo": {"raw": 4.84667, "fmt": "4.85"}, "30daysAgo": {"raw": 4.88, "fmt": "4.88"}, "60daysAgo": {"raw": 4.88, "fmt": "4.88"}, "90daysAgo": {"raw": 4.88, "fmt": "4.88"}, "epsTrendCurrency": "USD"}, "epsRevisions": {"upLast7days": {"raw": 1, "fmt": "1", "longFmt": "1"}, "upLast30days": {"raw": 2, "fmt": "2", "longFmt": "2"}, "downLast30days": {"raw": 0, "fmt": null, "longFmt": "0"}, "downLast7Days": {"raw": 0, "fmt": null, "longFmt": "0"}, "downLast90days": {}, "epsRevisionsCurrency": "USD"}}, {"maxAge": 1, "period": "+1y", "endDate": "2026-12-31", "growth": {"raw": 0.0163, "fmt": "1.63%"}, "earningsEstimate": {"avg": {"raw": 5.095, "fmt": "5.09"}, "low": {"raw": 4.94, "fmt": "4.94"}, "high": {"raw": 5.26, "fmt": "5.26"}, "yearAgoEps": {"raw": 5.01333, "fmt": "5.01"}, "numberOfAnalysts": {"raw": 4, "fmt": "4", "longFmt": "4"}, "growth": {"raw": 0.0163, "fmt": "1.63%"}, "earningsCurrency": "USD"}, "revenueEstimate": {"avg": {"raw": 1085063670, "fmt": "1.09B", "longFmt": "1,085,063,670"}, "low": {"raw": 1073394000, "fmt": "1.07B", "longFmt": "1,073,394,000"}, "high": {"raw": 1094900000, "fmt": "1.09B", "longFmt": "1,094,900,000"}, "numberOfAnalysts": {"raw": 3, "fmt": "3", "longFmt": "3"}, "yearAgoRevenue": {"raw": 1064590000, "fmt": "1.06B", "longFmt": "1,064,590,000"}, "growth": {"raw": 0.019199999, "fmt": "1.92%"}, "revenueCurrency": "USD"}, "epsTrend": {"current": {"raw": 5.095, "fmt": "5.09"}, "7daysAgo": {"raw": 5.1225, "fmt": "5.12"}, "30daysAgo": {"raw": 5.188, "fmt": "5.19"}, "60daysAgo": {"raw": 5.135, "fmt": "5.14"}, "90daysAgo": {"raw": 5.135, "fmt": "5.14"}, "epsTrendCurrency": "USD"}, "epsRevisions": {"upLast7days": {"raw": 1, "fmt": "1", "longFmt": "1"}, "upLast30days": {"raw": 1, "fmt": "1", "longFmt": "1"}, "downLast30days": {"raw": 2, "fmt": "2", "longFmt": "2"}, "downLast7Days": {"raw": 1, "fmt": "1", "longFmt": "1"}, "downLast90days": {}, "epsRevisionsCurrency": "USD"}}], "defaultMethodology": "nongaap", "maxAge": 1}, "earningsHistory": {"history": [{"maxAge": 1, "epsActual": {"raw": 1.11, "fmt": "1.11"}, "epsEstimate": {"raw": 0.99, "fmt": "0.99"}, "epsDifference": {"raw": 0.12, "fmt": "0.12"}, "surprisePercent": {"raw": 0.121199995, "fmt": "12.12%"}, "quarter": {"raw": 1735603200, "fmt": "2024-12-31"}, "currency": "USD", "period": "-4q"}, {"maxAge": 1, "epsActual": {"raw": 1.13, "fmt": "1.13"}, "epsEstimate": {"raw": 1.04, "fmt": "1.04"}, "epsDifference": {"raw": 0.09, "fmt": "0.09"}, "surprisePercent": {"raw": 0.0865, "fmt": "8.65%"}, "quarter": {"raw": 1743379200, "fmt": "2025-03-31"}, "currency": "USD", "period": "-3q"}, {"maxAge": 1, "epsActual": {"raw": 1.27, "fmt": "1.27"}, "epsEstimate": {"raw": 1.1325, "fmt": "1.13"}, "epsDifference": {"raw": 0.14, "fmt": "0.14"}, "surprisePercent": {"raw": 0.121400006, "fmt": "12.14%"}, "quarter": {"raw": 1751241600, "fmt": "2025-06-30"}, "currency": "USD", "period": "-2q"}, {"maxAge": 1, "epsActual": {"raw": 1.4, "fmt": "1.4"}, "epsEstimate": {"raw": 1.2525, "fmt": "1.25"}, "epsDifference": {"raw": 0.15, "fmt": "0.15"}, "surprisePercent": {"raw": 0.1178, "fmt": "11.78%"}, "quarter": {"raw": 1759190400, "fmt": "2025-09-30"}, "currency": "USD", "period": "-1q"}], "defaultMethodology": "nongaap", "maxAge": 86400}, "financialData": {"maxAge": 86400, "currentPrice": {"raw": 52.42, "fmt": "52.42"}, "targetHighPrice": {"raw": 66.0, "fmt": "66.00"}, "targetLowPrice": {"raw": 59.0, "fmt": "59.00"}, "targetMeanPrice": {"raw": 63.25, "fmt": "63.25"}, "targetMedianPrice": {"raw": 64.0, "fmt": "64.00"}, "recommendationMean": {"raw": 2.0, "fmt": "2.00"}, "recommendationKey": "buy", "numberOfAnalystOpinions": {"raw": 4, "fmt": "4", "longFmt": "4"}, "totalCash": {"raw": 1564273024, "fmt": "1.56B", "longFmt": "1,564,273,024"}, "totalCashPerShare": {"raw": 28.222, "fmt": "28.22"}, "ebitda": {}, "totalDebt": {"raw": 255099008, "fmt": "255.1M", "longFmt": "255,099,008"}, "quickRatio": {}, "currentRatio": {}, "totalRevenue": {"raw": 1011052032, "fmt": "1.01B", "longFmt": "1,011,052,032"}, "debtToEquity": {}, "revenuePerShare": {"raw": 17.596, "fmt": "17.60"}, "returnOnAssets": {"raw": 0.013350001, "fmt": "1.34%"}, "returnOnEquity": {"raw": 0.10304, "fmt": "10.30%"}, "grossProfits": {"raw": 1011052032, "fmt": "1.01B", "longFmt": "1,011,052,032"}, "freeCashflow": {}, "operatingCashflow": {}, "earningsGrowth": {"raw": 0.265, "fmt": "26.50%"}, "revenueGrowth": {"raw": 0.059, "fmt": "5.90%"}, "grossMargins": {"raw": 0.0, "fmt": "0.00%"}, "ebitdaMargins": {"raw": 0.0, "fmt": "0.00%"}, "operatingMargins": {"raw": 0.40091, "fmt": "40.09%"}, "profitMargins": {"raw": 0.27582002, "fmt": "27.58%"}, "financialCurrency": "USD"}}